cpu/data_mem.sv
module data_mem (
    input logic             clk,
    input logic [31:0]      A,
    input logic             WE,
    input logic [31:0]      WD,
    output logic [31:0]     RD
);

logic [31:0] data_array [32'h1FFFF:32'h0];

always_ff @(posedge clk)
    begin
    if (WE == 1'b1)
        data_array[A] <= WD;
    end

always_comb begin
    RD = data_array[A];
end

endmodule

LAB4/Task4/DataMemory/data_mem.vcd
$version Generated by VerilatedVcd $end
$date Tue Dec 13 15:47:07 2022 $end
$timescale 1ps $end

 $scope module TOP $end
  $var wire 32 + A [31:0] $end
  $var wire 32 - RD [31:0] $end
  $var wire 32 , WD [31:0] $end
  $var wire  1 * WE $end
  $var wire  1 ) clk $end
  $scope module data_mem $end
   $var wire 32 + A [31:0] $end
   $var wire 32 - RD [31:0] $end
   $var wire 32 , WD [31:0] $end
   $var wire  1 * WE $end
   $var wire  1 ) clk $end
   $var wire 32 # data_array[0] [31:0] $end
   $var wire 32 $ data_array[1] [31:0] $end
   $var wire 32 % data_array[2] [31:0] $end
   $var wire 32 & data_array[3] [31:0] $end
   $var wire 32 ' data_array[4] [31:0] $end
   $var wire 32 ( data_array[5] [31:0] $end
  $upscope $end
 $upscope $end
$enddefinitions $end


#0
b00000000000000000000000000000000 #
b00000000000000000000000000000000 $
b00000000000000000000000000000000 %
b00000000000000000000000000000000 &
b00000000000000000000000000000000 '
b00000000000000000000000000000000 (
1)
0*
b00000000000000000000000000000000 +
b00000000000000000000000000000001 ,
b00000000000000000000000000000000 -
#1
b00111110100100000000000010010011 #
b00111110100000000000000100010011 $
b00000000001000001001011001100011 %
b00111110100000000000000010010011 &
b00111110100000000000000100010011 '
0)
#2
1)
b00000000000000000000000000000100 +
b00111110100100000000000010010011 -
#3
0)
#4
1)
b00000000000000000000000000001000 +
b00111110100000000000000100010011 -
#5
0)
#6
1)
1*
b00000000000000000000000000001100 +
b00000000001000001001011001100011 -
#7
0)
#8
b00000000000000000000000000000001 &
1)
0*
b00000000000000000000000000010000 +
#9
0)
#10
1)
b00000000000000000000000000010100 +
b00111110100000000000000100010011 -
#11
0)
#12
1)
b00000000000000000000000000011000 +
b00000000000000000000000000000000 -
#13
0)
#14
1)
b00000000000000000000000000011100 +
#15
0)
#16
1)
b00000000000000000000000000100000 +
#17
0)
#18
1)
b00000000000000000000000000100100 +
b00111110100100000000000010010011 -
#19
0)
#20
1)
b00000000000000000000000000101000 +
b00111110100000000000000100010011 -
#21
0)
#22
1)
b00000000000000000000000000101100 +
b00000000001000001001011001100011 -
#23
0)
#24
1)
b00000000000000000000000000110000 +
b00000000000000000000000000000001 -
#25
0)
#26
1)
b00000000000000000000000000110100 +
b00111110100000000000000100010011 -
#27
0)
#28
1)
b00000000000000000000000000111000 +
b00000000000000000000000000000000 -
#29
0)
#30
1)
b00000000000000000000000000111100 +
#31
0)
#32
1)
b00000000000000000000000001000000 +
#33
0)
#34
1)
b00000000000000000000000001000100 +
b00111110100100000000000010010011 -
#35
0)
#36
1)
b00000000000000000000000001001000 +
b00111110100000000000000100010011 -
#37
0)
#38
1)
b00000000000000000000000001001100 +
b00000000001000001001011001100011 -
#39
0)
#40
1)
b00000000000000000000000001010000 +
b00000000000000000000000000000001 -
#41
0)
#42
1)
b00000000000000000000000001010100 +
b00111110100000000000000100010011 -
#43
0)
#44
1)
b00000000000000000000000001011000 +
b00000000000000000000000000000000 -
#45
0)
#46
1)
b00000000000000000000000001011100 +
#47
0)
#48
1)
b00000000000000000000000001100000 +
#49
0)
#50
1)
b00000000000000000000000001100100 +
b00111110100100000000000010010011 -
#51
0)
#52
1)
b00000000000000000000000001101000 +
b00111110100000000000000100010011 -
#53
0)
#54
1)
b00000000000000000000000001101100 +
b00000000001000001001011001100011 -
