cpu/data_mem_mux.sv
module data_mem_mux (
    input logic               clk,
    input logic [31:0]      A,
    input logic             WE,
    input logic [31:0]      WD,
    input logic             Resultsrc,
    output logic [31:0]     Result
);

//logic [31:0] data_array [32'h1FFFF:32'h0];
logic [31:0] data_array [31:0];
logic [31:0] RD;

always_ff @(posedge clk)
    begin
    if (WE == 1'b1)
        data_array[A] <= WD;
    end

always_comb begin
    RD = data_array[A];
    Result = Resultsrc ? RD : A;
end

endmodule

cpu/ALU.sv
module ALU (
    input logic [31:0]      ALUop1,
    input logic [31:0]      RegOp2,
    input logic [2:0]       ALUctrl,
    input logic             ALUsrc,
    input logic [31:0]      ImmOp,
    input logic [31:0]      incPC,
    output logic [31:0]     ALUout,
    output logic            EQ
);

logic [31:0]      ALUop2;

assign ALUop2 = ALUsrc ? ImmOp : RegOp2;

always_comb 
    case (ALUctrl)
    3'b000: ALUout = ALUop1 + ALUop2; //ADD
    3'b001: ALUout = ALUop1 - ALUop2; //SUB
    3'b010: ALUout = ALUop1 & ALUop2; //AND
    3'b011: ALUout = ALUop1 | ALUop2; //OR
    3'b101: ALUout = {{31{1'b0}},(ALUop1 < ALUop2)}; // output lowest 8 bits
    3'b111: ALUout = incPC; // calculate (PC + 4) for JAL
    default: ALUout = 32'b0;
    endcase

assign EQ = (ALUout == 32'b0);
endmodule

cpu/register.sv
module register (
    input logic             clk,
    input logic             trigger,
    input logic [4:0]       AD1,
    input logic [4:0]       AD2,
    input logic [4:0]       AD3,
    input logic             WE3,
    input logic [31:0]      WD3,
    output logic [31:0]     RD1,
    output logic [31:0]     RD2,
    output logic [31:0]     a0 [31:0]
);

logic [31:0] reg_array [31:0];

always_ff @(posedge clk) begin
    if (WE3 == 1'b1)
        reg_array[AD3] <= WD3;
        reg_array[0] <= 32'b0;
        reg_array[31] <= trigger;
end

always_comb begin
    RD1 = reg_array[AD1];
    RD2 = reg_array[AD2];
    a0 = reg_array;

end

endmodule

cpu/sign_ext.sv
module sign_ext (
    input logic [31:0]      Imm,
    input logic [1:0]       ImmSrc,
    output logic [31:0]     ImmOp
);

always_comb begin
    case(ImmSrc) 
        3'b00:
            ImmOp = {{20{Imm[31]}},Imm[31:20]}; //lw lbu
        3'b01:
            mmOp = {{Imm[31:12]}, 12'b0};   //LUI
        3'b10:
            ImmOp = {{20{Imm[31]}},Imm[7],Imm[30:25],Imm[11:8],1'b0}; //beq bne
        3'b11:
            ImmOp = {{12{Imm[31]}},Imm[19:12],Imm[20],Imm[30:21],1'b0}; //JAL
        default:
            ImmOp = {32'b0};
    endcase
end

endmodule

cpu/control.sv
module control(
    input logic         EQ,
    input logic [31:0]  Instr,
    output logic        RegWrite,
    output logic [2:0]  ALUctrl,
    output logic        ALUsrc,
    output logic [1:0]  ImmSrc,
    output logic        PCsrc,
    output logic        Resultsrc,
    output logic        Memwrite,
    output logic        reg_jump
);

logic [1:0]     ALUop;
logic [6:0]     Op;
logic [14:12]   funct3;
logic           funct7;
logic [20:0]    unused;

assign Op = Instr[6:0];
assign funct3 = Instr[14:12];
assign funct7 = Instr[30];
assign unused = {Instr[31], Instr[29:15], Instr[11:7]};

always_comb
    casez(Op)
        7'b0??????: RegWrite = 1; //for most instructions, if 1st opcode bit is 0, they write to register
        default: RegWrite = 0;
    endcase
    //need multiple casez
always_comb
    casez(Op)
        7'b00?????: ALUsrc = 1; //for most instructions, if 2nd opcode bit is 0 then it uses immediates
        default: ALUsrc = 0;
    endcase


always_latch
    if (Op == 7'b0000011) begin  // Opcode = lw "Load Word"
        ALUop = 2'b00;
        PCsrc = 0;
        Memwrite = 0;
        Resultsrc = 1;
        reg_jump = 0;
    end

    else if (Op == 7'b0100011) begin // Opcode = sw "Store Word"
        ALUop = 2'b00;
        PCsrc = 0;
        Memwrite = 1;
        RegWrite = 0;
        reg_jump = 0;
        Resultsrc = 0;
    end

    else if (Op == 7'b0110011 | Op == 7'b0010011) begin // Opcode = R-type or li "load immediate"
        ALUop = 2'b10;
        ImmSrc = 2'b00;
        PCsrc = 0;
        Memwrite = 0;
        Resultsrc = 0;
        reg_jump = 0;
        Resultsrc = 0;
    end

    else if (Op == 7'b0110111) begin // Opcode = LUI
        ALUop = 2'b01;
        ImmSrc = 2'b00;
        PCsrc = 0;
        Memwrite = 0;
        Resultsrc = 0;
        reg_jump = 0;
    end

    else if ((Op == 7'b1100011) & (funct3 == 3'b000)) begin // Opcode = BEQ
        ALUop = 2'b01;
        ImmSrc = 2'b10;
        PCsrc = EQ;
        Memwrite = 0;
        reg_jump = 0;
        Resultsrc = 0;
    end

    else if ((Op == 7'b1100011) & (funct3 == 3'b001)) begin // Opcode = BNE
        ALUop = 2'b01;
        ImmSrc = 2'b10;
        PCsrc = ~EQ;
        Memwrite = 0;
        reg_jump = 0;
        Resultsrc = 0;
    end
    else if (Op == 7'b1101111) begin // JAL
        ALUop = 2'b11;
        ImmSrc = 2'b11;
        PCsrc = 1;
        Memwrite = 0;
        RegWrite = 1;
        reg_jump = 0;
        Resultsrc = 0;
    end
    else if (Op == 7'b1100111) begin // JALR
        ALUop = 2'b11;
        PCsrc = 1;
        Memwrite = 0;
        RegWrite = 1;
        reg_jump = 1;
        Resultsrc = 0;
    end
    else begin
        ALUop = 2'b00;
        PCsrc = 0;
        reg_jump = 0;
        Resultsrc = 0;
    end



always_latch

    if (ALUop == 2'b00)
        ALUctrl = 3'b000; // SW/LW

    else if (ALUop == 2'b01)
        ALUctrl = 3'b001; // SUBTRACT (BNE/BEQ)
    
    else if (ALUop == 2'b11)
        ALUctrl = 3'b111; //JAL
    
    else if ((ALUop == 2'b10) & (funct3 == 3'b110))
        ALUctrl = 3'b011; // OR

    else if ((ALUop == 2'b10) & (funct3 == 3'b111))
        ALUctrl = 3'b010; // AND

    else if ((ALUop == 2'b10) & (funct3 == 3'b010))begin
        ALUctrl = 3'b101; //SLT

        if(funct7 == 1 && Op[5] == 1)
            ALUctrl = 3'b001; // SUBTRACT
                
        else
            ALUctrl = 3'b000; // ADD
    end

endmodule

cpu/instr_mem.sv
module instr_mem (
    input logic [31:0]      A,
    output logic [31:0]     RD
);

logic [31:0] rom_array [12'hFFF:0];

initial begin
    $readmemh("instruction.mem", rom_array);
end;

assign RD = rom_array[A];

endmodule

cpu/pc.sv
module pc (
    input logic [31:0] ImmOp,
    input logic        clk,
    input logic        rst,
    input logic        PCsrc,
    input logic [31:0] reg_addr,
    input logic         reg_jump,
    output logic [31:0] PC_out,
    output logic [31:0] incPC
);

logic [31:0] branch_PC;
logic [31:0] inc_PC; 
logic [31:0] next_PC;

assign branch_PC = reg_jump ? reg_addr : PC_out + ImmOp;
assign inc_PC    = PC_out + 32'b100;
assign incPC    = PC_out + 32'b100;
assign next_PC   = PCsrc ? branch_PC : inc_PC;

always_ff @(posedge clk, posedge rst) 
    if (rst) PC_out <= 32'b0;
    else     PC_out <= next_PC;

endmodule

cpu/top.sv
module top (
    input logic             clk,
    input logic             rst,
    input logic             trigger,
    output logic [31:0]     a0 [31:0],
    output logic [7:0]      data_out
);

//pc.sv outputs
logic [31:0] PC;
logic [31:0] incPC;

pc pc(
    .ImmOp(ImmOp),
    .clk(clk),
    .rst(rst),
    .PCsrc(PCsrc),
    .PC_out(PC),
    .incPC(incPC),
    .reg_addr(Regop1),
    .reg_jump(reg_jump)
);


//instr_mem.sv outputs
logic [31:0] instr;
logic [4:0] rs1;
logic [4:0] rs2;
logic [4:0] rd;
logic [31:0] Imm;

instr_mem instr_mem(
    .A(PC),
    .RD(instr)
);


//control.sv outputs
logic       PCsrc;
logic       Resultsrc;
logic       MemWrite;
logic [2:0] ALUctrl;
logic       ALUsrc;
logic [1:0] ImmSrc;
logic       RegWrite;
logic       reg_jump;

control control(
    .EQ(EQ),
    .Instr(instr),
    .RegWrite(RegWrite),
    .ALUctrl(ALUctrl),
    .ALUsrc(ALUsrc),
    .PCsrc(PCsrc),
    .ImmSrc(ImmSrc),
    .Resultsrc(Resultsrc),
    .Memwrite(MemWrite),
    .reg_jump(reg_jump)
);


//sign_ext.sv outputs
logic [31:0] ImmOp;

sign_ext signextend(
    .Imm(Imm),
    .ImmSrc(ImmSrc),
    .ImmOp(ImmOp)
);


//register.sv outputs
logic [31:0] Regop1;
logic [31:0] Regop2;

register register(
    .clk(clk),
    .AD1(rs1),
    .AD2(rs2),
    .AD3(rd),
    .WE3(RegWrite),
    .WD3(Result),
    .RD1(Regop1),
    .RD2(Regop2),
    .a0(a0),
    .trigger(trigger)
);


//ALU.sv outputs
logic [31:0] ALUout;
logic       EQ;

ALU ALU(
    .ALUop1(Regop1),
    .RegOp2(Regop2),
    .ALUctrl(ALUctrl),
    .ImmOp(ImmOp),
    .ALUsrc(ALUsrc),
    .ALUout(ALUout),
    .incPC(incPC),
    .EQ(EQ)
);


//data_mem_mux.sv outputs
logic [31:0] Result;

data_mem_mux data_mem(
    .clk(clk),
    .A(ALUout),
    .WE(MemWrite),
    .WD(Regop2),
    .Resultsrc(Resultsrc),
    .Result(Result)
);


//instruction bus outputs
assign rs1 = instr[19:15];
assign rs2 = instr[24:20];
assign rd = instr[11:7];
assign Imm = instr[31:0];

//data_out bus
assign data_out[0] = a0[20][0];
assign data_out[1] = a0[20][1];
assign data_out[2] = a0[20][2];
assign data_out[3] = a0[20][3];
assign data_out[4] = a0[20][4];
assign data_out[5] = a0[20][5];
assign data_out[6] = a0[20][6];
assign data_out[7] = a0[20][7];

endmodule

cpu/top.vcd
$version Generated by VerilatedVcd $end
$date Wed Dec 14 14:07:49 2022 $end
$timescale 1ps $end

 $scope module TOP $end
  $var wire 32 $! a0[0] [31:0] $end
  $var wire 32 .! a0[10] [31:0] $end
  $var wire 32 /! a0[11] [31:0] $end
  $var wire 32 0! a0[12] [31:0] $end
  $var wire 32 1! a0[13] [31:0] $end
  $var wire 32 2! a0[14] [31:0] $end
  $var wire 32 3! a0[15] [31:0] $end
  $var wire 32 4! a0[16] [31:0] $end
  $var wire 32 5! a0[17] [31:0] $end
  $var wire 32 6! a0[18] [31:0] $end
  $var wire 32 7! a0[19] [31:0] $end
  $var wire 32 %! a0[1] [31:0] $end
  $var wire 32 8! a0[20] [31:0] $end
  $var wire 32 9! a0[21] [31:0] $end
  $var wire 32 :! a0[22] [31:0] $end
  $var wire 32 ;! a0[23] [31:0] $end
  $var wire 32 <! a0[24] [31:0] $end
  $var wire 32 =! a0[25] [31:0] $end
  $var wire 32 >! a0[26] [31:0] $end
  $var wire 32 ?! a0[27] [31:0] $end
  $var wire 32 @! a0[28] [31:0] $end
  $var wire 32 A! a0[29] [31:0] $end
  $var wire 32 &! a0[2] [31:0] $end
  $var wire 32 B! a0[30] [31:0] $end
  $var wire 32 C! a0[31] [31:0] $end
  $var wire 32 '! a0[3] [31:0] $end
  $var wire 32 (! a0[4] [31:0] $end
  $var wire 32 )! a0[5] [31:0] $end
  $var wire 32 *! a0[6] [31:0] $end
  $var wire 32 +! a0[7] [31:0] $end
  $var wire 32 ,! a0[8] [31:0] $end
  $var wire 32 -! a0[9] [31:0] $end
  $var wire  1 !! clk $end
  $var wire  8 D! data_out [7:0] $end
  $var wire  1 "! rst $end
  $var wire  1 #! trigger $end
  $scope module top $end
   $var wire  3 m ALUctrl [2:0] $end
   $var wire 32 u ALUout [31:0] $end
   $var wire  1 n ALUsrc $end
   $var wire  1 v EQ $end
   $var wire 32 f Imm [31:0] $end
   $var wire 32 r ImmOp [31:0] $end
   $var wire  2 o ImmSrc [1:0] $end
   $var wire  1 l MemWrite $end
   $var wire 32 d PC [31:0] $end
   $var wire  1 j PCsrc $end
   $var wire  1 p RegWrite $end
   $var wire 32 s Regop1 [31:0] $end
   $var wire 32 t Regop2 [31:0] $end
   $var wire 32 E! Result [31:0] $end
   $var wire  1 k Resultsrc $end
   $var wire 32 $! a0[0] [31:0] $end
   $var wire 32 .! a0[10] [31:0] $end
   $var wire 32 /! a0[11] [31:0] $end
   $var wire 32 0! a0[12] [31:0] $end
   $var wire 32 1! a0[13] [31:0] $end
   $var wire 32 2! a0[14] [31:0] $end
   $var wire 32 3! a0[15] [31:0] $end
   $var wire 32 4! a0[16] [31:0] $end
   $var wire 32 5! a0[17] [31:0] $end
   $var wire 32 6! a0[18] [31:0] $end
   $var wire 32 7! a0[19] [31:0] $end
   $var wire 32 %! a0[1] [31:0] $end
   $var wire 32 8! a0[20] [31:0] $end
   $var wire 32 9! a0[21] [31:0] $end
   $var wire 32 :! a0[22] [31:0] $end
   $var wire 32 ;! a0[23] [31:0] $end
   $var wire 32 <! a0[24] [31:0] $end
   $var wire 32 =! a0[25] [31:0] $end
   $var wire 32 >! a0[26] [31:0] $end
   $var wire 32 ?! a0[27] [31:0] $end
   $var wire 32 @! a0[28] [31:0] $end
   $var wire 32 A! a0[29] [31:0] $end
   $var wire 32 &! a0[2] [31:0] $end
   $var wire 32 B! a0[30] [31:0] $end
   $var wire 32 C! a0[31] [31:0] $end
   $var wire 32 '! a0[3] [31:0] $end
   $var wire 32 (! a0[4] [31:0] $end
   $var wire 32 )! a0[5] [31:0] $end
   $var wire 32 *! a0[6] [31:0] $end
   $var wire 32 +! a0[7] [31:0] $end
   $var wire 32 ,! a0[8] [31:0] $end
   $var wire 32 -! a0[9] [31:0] $end
   $var wire  1 !! clk $end
   $var wire  8 D! data_out [7:0] $end
   $var wire 32 e incPC [31:0] $end
   $var wire 32 f instr [31:0] $end
   $var wire  5 i rd [4:0] $end
   $var wire  1 q reg_jump $end
   $var wire  5 g rs1 [4:0] $end
   $var wire  5 h rs2 [4:0] $end
   $var wire  1 "! rst $end
   $var wire  1 #! trigger $end
   $scope module ALU $end
    $var wire  3 m ALUctrl [2:0] $end
    $var wire 32 s ALUop1 [31:0] $end
    $var wire 32 w ALUop2 [31:0] $end
    $var wire 32 u ALUout [31:0] $end
    $var wire  1 n ALUsrc $end
    $var wire  1 v EQ $end
    $var wire 32 r ImmOp [31:0] $end
    $var wire 32 t RegOp2 [31:0] $end
    $var wire 32 e incPC [31:0] $end
   $upscope $end
   $scope module control $end
    $var wire  3 m ALUctrl [2:0] $end
    $var wire  2 x ALUop [1:0] $end
    $var wire  1 n ALUsrc $end
    $var wire  1 v EQ $end
    $var wire  2 o ImmSrc [1:0] $end
    $var wire 32 f Instr [31:0] $end
    $var wire  1 l Memwrite $end
    $var wire  7 y Op [6:0] $end
    $var wire  1 j PCsrc $end
    $var wire  1 p RegWrite $end
    $var wire  1 k Resultsrc $end
    $var wire  3 z funct3 [14:12] $end
    $var wire  1 { funct7 $end
    $var wire  1 q reg_jump $end
    $var wire 21 | unused [20:0] $end
   $upscope $end
   $scope module data_mem $end
    $var wire 32 u A [31:0] $end
    $var wire 32 # RD [31:0] $end
    $var wire 32 E! Result [31:0] $end
    $var wire  1 k Resultsrc $end
    $var wire 32 t WD [31:0] $end
    $var wire  1 l WE $end
    $var wire  1 !! clk $end
   $upscope $end
   $scope module instr_mem $end
    $var wire 32 d A [31:0] $end
    $var wire 32 f RD [31:0] $end
   $upscope $end
   $scope module pc $end
    $var wire 32 r ImmOp [31:0] $end
    $var wire 32 d PC_out [31:0] $end
    $var wire  1 j PCsrc $end
    $var wire 32 } branch_PC [31:0] $end
    $var wire  1 !! clk $end
    $var wire 32 e incPC [31:0] $end
    $var wire 32 e inc_PC [31:0] $end
    $var wire 32 ~ next_PC [31:0] $end
    $var wire 32 s reg_addr [31:0] $end
    $var wire  1 q reg_jump $end
    $var wire  1 "! rst $end
   $upscope $end
   $scope module register $end
    $var wire  5 g AD1 [4:0] $end
    $var wire  5 h AD2 [4:0] $end
    $var wire  5 i AD3 [4:0] $end
    $var wire 32 s RD1 [31:0] $end
    $var wire 32 t RD2 [31:0] $end
    $var wire 32 E! WD3 [31:0] $end
    $var wire  1 p WE3 $end
    $var wire 32 $ a0[0] [31:0] $end
    $var wire 32 . a0[10] [31:0] $end
    $var wire 32 / a0[11] [31:0] $end
    $var wire 32 0 a0[12] [31:0] $end
    $var wire 32 1 a0[13] [31:0] $end
    $var wire 32 2 a0[14] [31:0] $end
    $var wire 32 3 a0[15] [31:0] $end
    $var wire 32 4 a0[16] [31:0] $end
    $var wire 32 5 a0[17] [31:0] $end
    $var wire 32 6 a0[18] [31:0] $end
    $var wire 32 7 a0[19] [31:0] $end
    $var wire 32 % a0[1] [31:0] $end
    $var wire 32 8 a0[20] [31:0] $end
    $var wire 32 9 a0[21] [31:0] $end
    $var wire 32 : a0[22] [31:0] $end
    $var wire 32 ; a0[23] [31:0] $end
    $var wire 32 < a0[24] [31:0] $end
    $var wire 32 = a0[25] [31:0] $end
    $var wire 32 > a0[26] [31:0] $end
    $var wire 32 ? a0[27] [31:0] $end
    $var wire 32 @ a0[28] [31:0] $end
    $var wire 32 A a0[29] [31:0] $end
    $var wire 32 & a0[2] [31:0] $end
    $var wire 32 B a0[30] [31:0] $end
    $var wire 32 C a0[31] [31:0] $end
    $var wire 32 ' a0[3] [31:0] $end
    $var wire 32 ( a0[4] [31:0] $end
    $var wire 32 ) a0[5] [31:0] $end
    $var wire 32 * a0[6] [31:0] $end
    $var wire 32 + a0[7] [31:0] $end
    $var wire 32 , a0[8] [31:0] $end
    $var wire 32 - a0[9] [31:0] $end
    $var wire  1 !! clk $end
    $var wire 32 D reg_array[0] [31:0] $end
    $var wire 32 N reg_array[10] [31:0] $end
    $var wire 32 O reg_array[11] [31:0] $end
    $var wire 32 P reg_array[12] [31:0] $end
    $var wire 32 Q reg_array[13] [31:0] $end
    $var wire 32 R reg_array[14] [31:0] $end
    $var wire 32 S reg_array[15] [31:0] $end
    $var wire 32 T reg_array[16] [31:0] $end
    $var wire 32 U reg_array[17] [31:0] $end
    $var wire 32 V reg_array[18] [31:0] $end
    $var wire 32 W reg_array[19] [31:0] $end
    $var wire 32 E reg_array[1] [31:0] $end
    $var wire 32 X reg_array[20] [31:0] $end
    $var wire 32 Y reg_array[21] [31:0] $end
    $var wire 32 Z reg_array[22] [31:0] $end
    $var wire 32 [ reg_array[23] [31:0] $end
    $var wire 32 \ reg_array[24] [31:0] $end
    $var wire 32 ] reg_array[25] [31:0] $end
    $var wire 32 ^ reg_array[26] [31:0] $end
    $var wire 32 _ reg_array[27] [31:0] $end
    $var wire 32 ` reg_array[28] [31:0] $end
    $var wire 32 a reg_array[29] [31:0] $end
    $var wire 32 F reg_array[2] [31:0] $end
    $var wire 32 b reg_array[30] [31:0] $end
    $var wire 32 c reg_array[31] [31:0] $end
    $var wire 32 G reg_array[3] [31:0] $end
    $var wire 32 H reg_array[4] [31:0] $end
    $var wire 32 I reg_array[5] [31:0] $end
    $var wire 32 J reg_array[6] [31:0] $end
    $var wire 32 K reg_array[7] [31:0] $end
    $var wire 32 L reg_array[8] [31:0] $end
    $var wire 32 M reg_array[9] [31:0] $end
    $var wire  1 #! trigger $end
   $upscope $end
   $scope module signextend $end
    $var wire 32 f Imm [31:0] $end
    $var wire 32 r ImmOp [31:0] $end
    $var wire  2 o ImmSrc [1:0] $end
   $upscope $end
  $upscope $end
 $upscope $end
$enddefinitions $end


#0
b00000000000000000000000000000000 #
b00000000000000000000000000000000 $
b00000000000000000000000000000000 %
b00000000000000000000000000000000 &
b00000000000000000000000000000000 '
b00000000000000000000000000000000 (
b00000000000000000000000000000000 )
b00000000000000000000000000000000 *
b00000000000000000000000000000000 +
b00000000000000000000000000000000 ,
b00000000000000000000000000000000 -
b00000000000000000000000000000000 .
b00000000000000000000000000000000 /
b00000000000000000000000000000000 0
b00000000000000000000000000000000 1
b00000000000000000000000000000000 2
b00000000000000000000000000000000 3
b00000000000000000000000000000000 4
b00000000000000000000000000000000 5
b00000000000000000000000000000000 6
b00000000000000000000000000000000 7
b00000000000000000000000000000000 8
b00000000000000000000000000000000 9
b00000000000000000000000000000000 :
b00000000000000000000000000000000 ;
b00000000000000000000000000000000 <
b00000000000000000000000000000000 =
b00000000000000000000000000000000 >
b00000000000000000000000000000000 ?
b00000000000000000000000000000000 @
b00000000000000000000000000000000 A
b00000000000000000000000000000000 B
b00000000000000000000000000000000 C
b00000000000000000000000000000000 D
b00000000000000000000000000000000 E
b00000000000000000000000000000000 F
b00000000000000000000000000000000 G
b00000000000000000000000000000000 H
b00000000000000000000000000000000 I
b00000000000000000000000000000000 J
b00000000000000000000000000000000 K
b00000000000000000000000000000000 L
b00000000000000000000000000000000 M
b00000000000000000000000000000000 N
b00000000000000000000000000000000 O
b00000000000000000000000000000000 P
b00000000000000000000000000000000 Q
b00000000000000000000000000000000 R
b00000000000000000000000000000000 S
b00000000000000000000000000000000 T
b00000000000000000000000000000000 U
b00000000000000000000000000000000 V
b00000000000000000000000000000000 W
b00000000000000000000000000000000 X
b00000000000000000000000000000000 Y
b00000000000000000000000000000000 Z
b00000000000000000000000000000000 [
b00000000000000000000000000000000 \
b00000000000000000000000000000000 ]
b00000000000000000000000000000000 ^
b00000000000000000000000000000000 _
b00000000000000000000000000000000 `
b00000000000000000000000000000000 a
b00000000000000000000000000000000 b
b00000000000000000000000000000000 c
b00000000000000000000000000000000 d
b00000000000000000000000000000100 e
b00000000000000000000000000000000 f
b00000 g
b00000 h
b00000 i
0j
0k
0l
b000 m
1n
b00 o
0p
0q
b00000000000000000000000000000000 r
b00000000000000000000000000000000 s
b00000000000000000000000000000000 t
b00000000000000000000000000000000 u
1v
b00000000000000000000000000000000 w
b00 x
b0000000 y
b000 z
0{
b000000000000000000000 |
b00000000000000000000000000000000 }
b00000000000000000000000000000000 ~
0!!
0"!
0#!
b00000000000000000000000000000000 $!
b00000000000000000000000000000000 %!
b00000000000000000000000000000000 &!
b00000000000000000000000000000000 '!
b00000000000000000000000000000000 (!
b00000000000000000000000000000000 )!
b00000000000000000000000000000000 *!
b00000000000000000000000000000000 +!
b00000000000000000000000000000000 ,!
b00000000000000000000000000000000 -!
b00000000000000000000000000000000 .!
b00000000000000000000000000000000 /!
b00000000000000000000000000000000 0!
b00000000000000000000000000000000 1!
b00000000000000000000000000000000 2!
b00000000000000000000000000000000 3!
b00000000000000000000000000000000 4!
b00000000000000000000000000000000 5!
b00000000000000000000000000000000 6!
b00000000000000000000000000000000 7!
b00000000000000000000000000000000 8!
b00000000000000000000000000000000 9!
b00000000000000000000000000000000 :!
b00000000000000000000000000000000 ;!
b00000000000000000000000000000000 <!
b00000000000000000000000000000000 =!
b00000000000000000000000000000000 >!
b00000000000000000000000000000000 ?!
b00000000000000000000000000000000 @!
b00000000000000000000000000000000 A!
b00000000000000000000000000000000 B!
b00000000000000000000000000000000 C!
b00000000 D!
b00000000000000000000000000000000 E!
#1
b00000010000000000000010100010011 f
b01010 i
1p
b00000000000000000000000000100000 r
b00000000000000000000000000100000 u
0v
b00000000000000000000000000100000 w
b10 x
b0010011 y
b000001000000000001010 |
b00000000000000000000000000100000 }
b00000000000000000000000000000100 ~
1!!
b00000000000000000000000000100000 E!
#2
0!!
1#!
#3
b00000000000000000000000000100000 .
b00000000000000000000000000000001 C
b00000000000000000000000000100000 N
b00000000000000000000000000000001 c
b10111111110000000000000000000100 d
b10111111110000000000000000001000 e
b00000000000000000000011000010011 f
b01100 i
b00000000000000000000000000000000 r
b00000000000000000000000000000000 u
1v
b00000000000000000000000000000000 w
b000000000000000001100 |
b10111111110000000000000000000100 }
b10111111110000000000000000001000 ~
1!!
b00000000000000000000000000100000 .!
b00000000000000000000000000000001 C!
b00000000000000000000000000000000 E!
#4
0!!
#5
b01111111100000000000000000001000 d
b01111111100000000000000000001100 e
b00000000000000000000101000010011 f
b10100 i
b000000000000000010100 |
b01111111100000000000000000001000 }
b01111111100000000000000000001100 ~
1!!
#6
0!!
#7
b00111111010000000000000000001100 d
b00111111010000000000000000010000 e
b11111110000011111001111011100011 f
b11111 g
b11101 i
1j
b001 m
0n
b10 o
0p
b11111111111111111111111111111100 r
b00000000000000000000000000000001 s
b00000000000000000000000000000001 u
0v
b01 x
b1100011 y
b001 z
1{
b111111000001111111101 |
b00111111010000000000000000001000 }
b00111111010000000000000000001000 ~
1!!
b00000000000000000000000000000001 E!
#8
0!!
#9
b11111111000000000000000000001000 d
b11111111000000000000000000001100 e
b00000000000000000000101000010011 f
b00000 g
b10100 i
0j
b000 m
1n
b00 o
1p
b00000000000000000000000000000000 r
b00000000000000000000000000000000 s
b00000000000000000000000000000000 u
1v
b10 x
b0010011 y
b000 z
0{
b000000000000000010100 |
b11111111000000000000000000001000 }
b11111111000000000000000000001100 ~
1!!
b00000000000000000000000000000000 E!
#10
0!!
#11
b10111110110000000000000000001100 d
b10111110110000000000000000010000 e
b11111110000011111001111011100011 f
b11111 g
b11101 i
1j
b001 m
0n
b10 o
0p
b11111111111111111111111111111100 r
b00000000000000000000000000000001 s
b00000000000000000000000000000001 u
0v
b01 x
b1100011 y
b001 z
1{
b111111000001111111101 |
b10111110110000000000000000001000 }
b10111110110000000000000000001000 ~
1!!
b00000000000000000000000000000001 E!
#12
0!!
#13
b01111110100000000000000000001000 d
b01111110100000000000000000001100 e
b00000000000000000000101000010011 f
b00000 g
b10100 i
0j
b000 m
1n
b00 o
1p
b00000000000000000000000000000000 r
b00000000000000000000000000000000 s
b00000000000000000000000000000000 u
1v
b10 x
b0010011 y
b000 z
0{
b000000000000000010100 |
b01111110100000000000000000001000 }
b01111110100000000000000000001100 ~
1!!
b00000000000000000000000000000000 E!
#14
0!!
#15
b00111110010000000000000000001100 d
b00111110010000000000000000010000 e
b11111110000011111001111011100011 f
b11111 g
b11101 i
1j
b001 m
0n
b10 o
0p
b11111111111111111111111111111100 r
b00000000000000000000000000000001 s
b00000000000000000000000000000001 u
0v
b01 x
b1100011 y
b001 z
1{
b111111000001111111101 |
b00111110010000000000000000001000 }
b00111110010000000000000000001000 ~
1!!
b00000000000000000000000000000001 E!
#16
0!!
#17
b11111110000000000000000000001000 d
b11111110000000000000000000001100 e
b00000000000000000000101000010011 f
b00000 g
b10100 i
0j
b000 m
1n
b00 o
1p
b00000000000000000000000000000000 r
b00000000000000000000000000000000 s
b00000000000000000000000000000000 u
1v
b10 x
b0010011 y
b000 z
0{
b000000000000000010100 |
b11111110000000000000000000001000 }
b11111110000000000000000000001100 ~
1!!
b00000000000000000000000000000000 E!
#18
0!!
#19
b10111101110000000000000000001100 d
b10111101110000000000000000010000 e
b11111110000011111001111011100011 f
b11111 g
b11101 i
1j
b001 m
0n
b10 o
0p
b11111111111111111111111111111100 r
b00000000000000000000000000000001 s
b00000000000000000000000000000001 u
0v
b01 x
b1100011 y
b001 z
1{
b111111000001111111101 |
b10111101110000000000000000001000 }
b10111101110000000000000000001000 ~
1!!
b00000000000000000000000000000001 E!
#20
0!!
#21
b01111101100000000000000000001000 d
b01111101100000000000000000001100 e
b00000000000000000000101000010011 f
b00000 g
b10100 i
0j
b000 m
1n
b00 o
1p
b00000000000000000000000000000000 r
b00000000000000000000000000000000 s
b00000000000000000000000000000000 u
1v
b10 x
b0010011 y
b000 z
0{
b000000000000000010100 |
b01111101100000000000000000001000 }
b01111101100000000000000000001100 ~
1!!
b00000000000000000000000000000000 E!
#22
0!!
#23
b00111101010000000000000000001100 d
b00111101010000000000000000010000 e
b11111110000011111001111011100011 f
b11111 g
b11101 i
1j
b001 m
0n
b10 o
0p
b11111111111111111111111111111100 r
b00000000000000000000000000000001 s
b00000000000000000000000000000001 u
0v
b01 x
b1100011 y
b001 z
1{
b111111000001111111101 |
b00111101010000000000000000001000 }
b00111101010000000000000000001000 ~
1!!
b00000000000000000000000000000001 E!
#24
0!!
#25
b11111101000000000000000000001000 d
b11111101000000000000000000001100 e
b00000000000000000000101000010011 f
b00000 g
b10100 i
0j
b000 m
1n
b00 o
1p
b00000000000000000000000000000000 r
b00000000000000000000000000000000 s
b00000000000000000000000000000000 u
1v
b10 x
b0010011 y
b000 z
0{
b000000000000000010100 |
b11111101000000000000000000001000 }
b11111101000000000000000000001100 ~
1!!
b00000000000000000000000000000000 E!
#26
0!!
#27
b10111100110000000000000000001100 d
b10111100110000000000000000010000 e
b11111110000011111001111011100011 f
b11111 g
b11101 i
1j
b001 m
0n
b10 o
0p
b11111111111111111111111111111100 r
b00000000000000000000000000000001 s
b00000000000000000000000000000001 u
0v
b01 x
b1100011 y
b001 z
1{
b111111000001111111101 |
b10111100110000000000000000001000 }
b10111100110000000000000000001000 ~
1!!
b00000000000000000000000000000001 E!
#28
0!!
#29
b01111100100000000000000000001000 d
b01111100100000000000000000001100 e
b00000000000000000000101000010011 f
b00000 g
b10100 i
0j
b000 m
1n
b00 o
1p
b00000000000000000000000000000000 r
b00000000000000000000000000000000 s
b00000000000000000000000000000000 u
1v
b10 x
b0010011 y
b000 z
0{
b000000000000000010100 |
b01111100100000000000000000001000 }
b01111100100000000000000000001100 ~
1!!
b00000000000000000000000000000000 E!
#30
0!!
#31
b00111100010000000000000000001100 d
b00111100010000000000000000010000 e
b11111110000011111001111011100011 f
b11111 g
b11101 i
1j
b001 m
0n
b10 o
0p
b11111111111111111111111111111100 r
b00000000000000000000000000000001 s
b00000000000000000000000000000001 u
0v
b01 x
b1100011 y
b001 z
1{
b111111000001111111101 |
b00111100010000000000000000001000 }
b00111100010000000000000000001000 ~
1!!
b00000000000000000000000000000001 E!
#32
0!!
#33
b11111100000000000000000000001000 d
b11111100000000000000000000001100 e
b00000000000000000000101000010011 f
b00000 g
b10100 i
0j
b000 m
1n
b00 o
1p
b00000000000000000000000000000000 r
b00000000000000000000000000000000 s
b00000000000000000000000000000000 u
1v
b10 x
b0010011 y
b000 z
0{
b000000000000000010100 |
b11111100000000000000000000001000 }
b11111100000000000000000000001100 ~
1!!
b00000000000000000000000000000000 E!
#34
0!!
