cpu/data_mem_mux.sv
module data_mem_mux (
    input logic               clk,
    input logic [31:0]      A,
    input logic             WE,
    input logic [31:0]      WD,
    input logic             Resultsrc,
    output logic [31:0]     Result
);

//logic [31:0] data_array [32'h1FFFF:32'h0];
logic [31:0] data_array [31:0];
logic [31:0] RD;

always_ff @(posedge clk)
    begin
    if (WE == 1'b1)
        data_array[A] <= WD;
    end

always_comb begin
    RD = data_array[A];
    Result = Resultsrc ? RD : A;
end

endmodule

cpu/ALU.sv
module ALU (
    input logic [31:0]      ALUop1,
    input logic [31:0]      RegOp2,
    input logic [2:0]       ALUctrl,
    input logic             ALUsrc,
    input logic [31:0]       ImmOp,
    output logic [31:0]     ALUout,
    output logic            EQ
);

logic [31:0]      ALUop2;

assign ALUop2 = ALUsrc ? ImmOp : RegOp2;

always_comb 
    case (ALUctrl)
    3'b000: ALUout = ALUop1 + ALUop2; //ADD
    3'b001: ALUout = ALUop1 - ALUop2; //SUB
    3'b010: ALUout = ALUop1 & ALUop2; //AND
    3'b011: ALUout = ALUop1 | ALUop2; //OR
    3'b101: ALUout = {{31{1'b0}},(ALUop1 < ALUop2)}; //SLT
    default: ALUout = 32'b0;
    endcase

assign EQ = (ALUout == 32'b0);
endmodule

cpu/register.sv
module register (
    input logic             clk,
    input logic [4:0]       AD1,
    input logic [4:0]       AD2,
    input logic [4:0]       AD3,
    input logic             WE3,
    input logic [31:0]      WD3,
    output logic [31:0]     RD1,
    output logic [31:0]     RD2,
    output logic [31:0]     a0 [31:0]
);

logic [31:0] reg_array [31:0];

always_ff @(posedge clk) begin
    if (WE3 == 1'b1)
        reg_array[AD3] <= WD3;
end

always_comb begin
    RD1 = reg_array[AD1];
    RD2 = reg_array[AD2];
    a0 = reg_array;
end

endmodule

cpu/sign_ext.sv
module sign_ext (
    input logic [31:0]      Imm,
    input logic [1:0]       ImmSrc,
    output logic [31:0]     ImmOp
);

always_comb begin
    case(ImmSrc) 
        3'b00:
            ImmOp = {{20{Imm[31]}},Imm[31:20]}; //lw lbu
        3'b01:
            mmOp = {{Imm[31:12]}, 12'b0};   //LUI
        3'b10:
            ImmOp = {{20{Imm[31]}},Imm[7],Imm[30:25],Imm[11:8],1'b0}; //beq bne
        3'b11:
            ImmOp = {{12{Imm[31]}},Imm[19:12],Imm[20],Imm[30:21],1'b0}; //JAL
        default:
            ImmOp = {32'b0};
    endcase
end

endmodule

cpu/control.sv
module control(
    input logic         EQ,
    input logic [31:0]  Instr,
    output logic        RegWrite,
    output logic [2:0]  ALUctrl,
    output logic        ALUsrc,
    output logic [1:0]  ImmSrc,
    output logic        PCsrc,
    output logic        Resultsrc,
    output logic        Memwrite
);

logic [1:0]     ALUop;
logic [6:0]     Op;
logic [14:12]   funct3;
logic           funct7;
logic [20:0]    unused;

assign Op = Instr[6:0];
assign funct3 = Instr[14:12];
assign funct7 = Instr[30];
assign unused = {Instr[31], Instr[29:15], Instr[11:7]};

always_latch
    if (Op == 7'b0000011) begin  // Opcode = lw "Load Word"
        ALUop = 2'b00;
        RegWrite = 1;
        ImmSrc = 2'b00;
        PCsrc = 0;
        Memwrite = 0;
        Resultsrc = 1;
    end

    else if (Op == 7'b0100011) begin // Opcode = sw "Store Word"
        ALUop = 2'b00;
        RegWrite = 0;
        ImmSrc = 2'b01;
        PCsrc = 0;
        Memwrite = 1;
    end

    else if (Op == 7'b0110011) begin // Opcode = R-type 
        ALUop = 2'b10;
        RegWrite = 1;
        ImmSrc = 0;
        PCsrc = 0;
        Memwrite = 0;
        Resultsrc = 0;
    end

    else if (Op == 7'b1100011) begin // Opcode = beq "Branch if Equal"
        ALUop = 2'b01;
        RegWrite = 1;
        ImmSrc = 2'b10;
        PCsrc = EQ && 1;
        Memwrite = 0;
    end


always_latch

    if (ALUop == 2'b00)
        ALUctrl = 3'b000; // ADD (LW/SW)

    else if (ALUop == 2'b01)
        ALUctrl = 3'b001; // SUBTRACT (BEQ)

    else if (ALUop == 2'b10)

        if (funct3 == 3'b010)
            ALUctrl = 3'b101; // SET LESS THAN

        else if (funct3 == 3'b110)
            ALUctrl = 3'b011; // OR

        else if (funct3 == 3'b111)
            ALUctrl = 3'b010; // AND

        else if (funct3 == 3'b000)

            if(funct7 == 1 && Op[5] == 1)
                ALUctrl = 3'b001; // SUBTRACT
                
            else
                ALUctrl = 3'b000; // ADD

always_comb
    casez(Op)
        7'b0??????: RegWrite = 1; //for most instructions, if 1st opcode bit is 0, they write to register
        7'b?0?????: ALUsrc = 1; //for most instructions, if 2nd opcode bit is 0 then it uses immediates
        default: ALUsrc = 0;
    endcase

endmodule

cpu/instr_mem.sv
module instr_mem (
    input logic [31:0]      A,
    output logic [31:0]     RD
);

logic [31:0] rom_array [12'hFFF:0];

initial begin
    $readmemh("instruction.mem", rom_array);
end;

assign RD = rom_array[A];

endmodule

cpu/pc.sv
module pc (
    input logic [31:0] ImmOp,
    input logic        clk,
    input logic        rst,
    input logic        PCsrc,
    output logic [31:0] PC_out
);

logic [31:0] branch_PC;
logic [31:0] inc_PC; 
logic [31:0] next_PC;

assign branch_PC = PC_out + ImmOp;
assign inc_PC    = PC_out + 32'b100;
assign next_PC   = PCsrc ? branch_PC : inc_PC;

always_ff @(posedge clk, posedge rst) 
    if (rst) PC_out <= 32'b0;
    else     PC_out <= next_PC;

endmodule

cpu/top.sv
module top (
    input logic             clk,
    input logic             rst,
    output logic [31:0]     a0 [31:0]
);

//pc.sv outputs
logic [31:0] PC;

pc pc(
    .ImmOp(ImmOp),
    .clk(clk),
    .rst(rst),
    .PCsrc(PCsrc),
    .PC_out(PC)
);


//instr_mem.sv outputs
logic [31:0] instr;
logic [4:0] rs1;
logic [4:0] rs2;
logic [4:0] rd;
logic [31:0] Imm;

instr_mem instr_mem(
    .A(PC),
    .RD(instr)
);


//control.sv outputs
logic       PCsrc;
logic       Resultsrc;
logic       MemWrite;
logic [2:0] ALUctrl;
logic       ALUsrc;
logic [1:0] ImmSrc;
logic       RegWrite;

control control(
    .EQ(EQ),
    .Instr(instr),
    .RegWrite(RegWrite),
    .ALUctrl(ALUctrl),
    .ALUsrc(ALUsrc),
    .PCsrc(PCsrc),
    .ImmSrc(ImmSrc),
    .Resultsrc(Resultsrc),
    .Memwrite(MemWrite)
);


//sign_ext.sv outputs
logic [31:0] ImmOp;

sign_ext signextend(
    .Imm(Imm),
    .ImmSrc(ImmSrc),
    .ImmOp(ImmOp)
);


//register.sv outputs
logic [31:0] Regop1;
logic [31:0] Regop2;

register register(
    .clk(clk),
    .AD1(rs1),
    .AD2(rs2),
    .AD3(rd),
    .WE3(RegWrite),
    .WD3(Result),
    .RD1(Regop1),
    .RD2(Regop2),
    .a0(a0)
);


//ALU.sv outputs
logic [31:0] ALUout;
logic       EQ;

ALU ALU(
    .ALUop1(Regop1),
    .RegOp2(Regop2),
    .ALUctrl(ALUctrl),
    .ImmOp(ImmOp),
    .ALUsrc(ALUsrc),
    .ALUout(ALUout),
    .EQ(EQ)
);


//data_mem_mux.sv outputs
logic [31:0] Result;

data_mem_mux data_mem(
    .clk(clk),
    .A(ALUout),
    .WE(MemWrite),
    .WD(Regop2),
    .Resultsrc(Resultsrc),
    .Result(Result)
);


//instruction bus outputs
assign rs1 = instr[19:15];
assign rs2 = instr[24:20];
assign rd = instr[11:7];
assign Imm = instr[31:0];

endmodule

cpu/top.vcd
$version Generated by VerilatedVcd $end
$date Fri Dec  9 21:45:27 2022 $end
$timescale 1ps $end

 $scope module TOP $end
  $var wire 32 "! a0[0] [31:0] $end
  $var wire 32 ,! a0[10] [31:0] $end
  $var wire 32 -! a0[11] [31:0] $end
  $var wire 32 .! a0[12] [31:0] $end
  $var wire 32 /! a0[13] [31:0] $end
  $var wire 32 0! a0[14] [31:0] $end
  $var wire 32 1! a0[15] [31:0] $end
  $var wire 32 2! a0[16] [31:0] $end
  $var wire 32 3! a0[17] [31:0] $end
  $var wire 32 4! a0[18] [31:0] $end
  $var wire 32 5! a0[19] [31:0] $end
  $var wire 32 #! a0[1] [31:0] $end
  $var wire 32 6! a0[20] [31:0] $end
  $var wire 32 7! a0[21] [31:0] $end
  $var wire 32 8! a0[22] [31:0] $end
  $var wire 32 9! a0[23] [31:0] $end
  $var wire 32 :! a0[24] [31:0] $end
  $var wire 32 ;! a0[25] [31:0] $end
  $var wire 32 <! a0[26] [31:0] $end
  $var wire 32 =! a0[27] [31:0] $end
  $var wire 32 >! a0[28] [31:0] $end
  $var wire 32 ?! a0[29] [31:0] $end
  $var wire 32 $! a0[2] [31:0] $end
  $var wire 32 @! a0[30] [31:0] $end
  $var wire 32 A! a0[31] [31:0] $end
  $var wire 32 %! a0[3] [31:0] $end
  $var wire 32 &! a0[4] [31:0] $end
  $var wire 32 '! a0[5] [31:0] $end
  $var wire 32 (! a0[6] [31:0] $end
  $var wire 32 )! a0[7] [31:0] $end
  $var wire 32 *! a0[8] [31:0] $end
  $var wire 32 +! a0[9] [31:0] $end
  $var wire  1 ~ clk $end
  $var wire  1 !! rst $end
  $scope module top $end
   $var wire  3 l ALUctrl [2:0] $end
   $var wire 32 s ALUout [31:0] $end
   $var wire  1 m ALUsrc $end
   $var wire  1 t EQ $end
   $var wire 32 e Imm [31:0] $end
   $var wire 32 p ImmOp [31:0] $end
   $var wire  2 n ImmSrc [1:0] $end
   $var wire  1 k MemWrite $end
   $var wire 32 d PC [31:0] $end
   $var wire  1 i PCsrc $end
   $var wire  1 o RegWrite $end
   $var wire 32 q Regop1 [31:0] $end
   $var wire 32 r Regop2 [31:0] $end
   $var wire 32 B! Result [31:0] $end
   $var wire  1 j Resultsrc $end
   $var wire 32 "! a0[0] [31:0] $end
   $var wire 32 ,! a0[10] [31:0] $end
   $var wire 32 -! a0[11] [31:0] $end
   $var wire 32 .! a0[12] [31:0] $end
   $var wire 32 /! a0[13] [31:0] $end
   $var wire 32 0! a0[14] [31:0] $end
   $var wire 32 1! a0[15] [31:0] $end
   $var wire 32 2! a0[16] [31:0] $end
   $var wire 32 3! a0[17] [31:0] $end
   $var wire 32 4! a0[18] [31:0] $end
   $var wire 32 5! a0[19] [31:0] $end
   $var wire 32 #! a0[1] [31:0] $end
   $var wire 32 6! a0[20] [31:0] $end
   $var wire 32 7! a0[21] [31:0] $end
   $var wire 32 8! a0[22] [31:0] $end
   $var wire 32 9! a0[23] [31:0] $end
   $var wire 32 :! a0[24] [31:0] $end
   $var wire 32 ;! a0[25] [31:0] $end
   $var wire 32 <! a0[26] [31:0] $end
   $var wire 32 =! a0[27] [31:0] $end
   $var wire 32 >! a0[28] [31:0] $end
   $var wire 32 ?! a0[29] [31:0] $end
   $var wire 32 $! a0[2] [31:0] $end
   $var wire 32 @! a0[30] [31:0] $end
   $var wire 32 A! a0[31] [31:0] $end
   $var wire 32 %! a0[3] [31:0] $end
   $var wire 32 &! a0[4] [31:0] $end
   $var wire 32 '! a0[5] [31:0] $end
   $var wire 32 (! a0[6] [31:0] $end
   $var wire 32 )! a0[7] [31:0] $end
   $var wire 32 *! a0[8] [31:0] $end
   $var wire 32 +! a0[9] [31:0] $end
   $var wire  1 ~ clk $end
   $var wire 32 e instr [31:0] $end
   $var wire  5 h rd [4:0] $end
   $var wire  5 f rs1 [4:0] $end
   $var wire  5 g rs2 [4:0] $end
   $var wire  1 !! rst $end
   $scope module ALU $end
    $var wire  3 l ALUctrl [2:0] $end
    $var wire 32 q ALUop1 [31:0] $end
    $var wire 32 u ALUop2 [31:0] $end
    $var wire 32 s ALUout [31:0] $end
    $var wire  1 m ALUsrc $end
    $var wire  1 t EQ $end
    $var wire 32 p ImmOp [31:0] $end
    $var wire 32 r RegOp2 [31:0] $end
   $upscope $end
   $scope module control $end
    $var wire  3 l ALUctrl [2:0] $end
    $var wire  2 v ALUop [1:0] $end
    $var wire  1 m ALUsrc $end
    $var wire  1 t EQ $end
    $var wire  2 n ImmSrc [1:0] $end
    $var wire 32 e Instr [31:0] $end
    $var wire  1 k Memwrite $end
    $var wire  7 w Op [6:0] $end
    $var wire  1 i PCsrc $end
    $var wire  1 o RegWrite $end
    $var wire  1 j Resultsrc $end
    $var wire  3 x funct3 [14:12] $end
    $var wire  1 y funct7 $end
    $var wire 21 z unused [20:0] $end
   $upscope $end
   $scope module data_mem $end
    $var wire 32 s A [31:0] $end
    $var wire 32 # RD [31:0] $end
    $var wire 32 B! Result [31:0] $end
    $var wire  1 j Resultsrc $end
    $var wire 32 r WD [31:0] $end
    $var wire  1 k WE $end
    $var wire  1 ~ clk $end
   $upscope $end
   $scope module instr_mem $end
    $var wire 32 d A [31:0] $end
    $var wire 32 e RD [31:0] $end
   $upscope $end
   $scope module pc $end
    $var wire 32 p ImmOp [31:0] $end
    $var wire 32 d PC_out [31:0] $end
    $var wire  1 i PCsrc $end
    $var wire 32 { branch_PC [31:0] $end
    $var wire  1 ~ clk $end
    $var wire 32 | inc_PC [31:0] $end
    $var wire 32 } next_PC [31:0] $end
    $var wire  1 !! rst $end
   $upscope $end
   $scope module register $end
    $var wire  5 f AD1 [4:0] $end
    $var wire  5 g AD2 [4:0] $end
    $var wire  5 h AD3 [4:0] $end
    $var wire 32 q RD1 [31:0] $end
    $var wire 32 r RD2 [31:0] $end
    $var wire 32 B! WD3 [31:0] $end
    $var wire  1 o WE3 $end
    $var wire 32 $ a0[0] [31:0] $end
    $var wire 32 . a0[10] [31:0] $end
    $var wire 32 / a0[11] [31:0] $end
    $var wire 32 0 a0[12] [31:0] $end
    $var wire 32 1 a0[13] [31:0] $end
    $var wire 32 2 a0[14] [31:0] $end
    $var wire 32 3 a0[15] [31:0] $end
    $var wire 32 4 a0[16] [31:0] $end
    $var wire 32 5 a0[17] [31:0] $end
    $var wire 32 6 a0[18] [31:0] $end
    $var wire 32 7 a0[19] [31:0] $end
    $var wire 32 % a0[1] [31:0] $end
    $var wire 32 8 a0[20] [31:0] $end
    $var wire 32 9 a0[21] [31:0] $end
    $var wire 32 : a0[22] [31:0] $end
    $var wire 32 ; a0[23] [31:0] $end
    $var wire 32 < a0[24] [31:0] $end
    $var wire 32 = a0[25] [31:0] $end
    $var wire 32 > a0[26] [31:0] $end
    $var wire 32 ? a0[27] [31:0] $end
    $var wire 32 @ a0[28] [31:0] $end
    $var wire 32 A a0[29] [31:0] $end
    $var wire 32 & a0[2] [31:0] $end
    $var wire 32 B a0[30] [31:0] $end
    $var wire 32 C a0[31] [31:0] $end
    $var wire 32 ' a0[3] [31:0] $end
    $var wire 32 ( a0[4] [31:0] $end
    $var wire 32 ) a0[5] [31:0] $end
    $var wire 32 * a0[6] [31:0] $end
    $var wire 32 + a0[7] [31:0] $end
    $var wire 32 , a0[8] [31:0] $end
    $var wire 32 - a0[9] [31:0] $end
    $var wire  1 ~ clk $end
    $var wire 32 D reg_array[0] [31:0] $end
    $var wire 32 N reg_array[10] [31:0] $end
    $var wire 32 O reg_array[11] [31:0] $end
    $var wire 32 P reg_array[12] [31:0] $end
    $var wire 32 Q reg_array[13] [31:0] $end
    $var wire 32 R reg_array[14] [31:0] $end
    $var wire 32 S reg_array[15] [31:0] $end
    $var wire 32 T reg_array[16] [31:0] $end
    $var wire 32 U reg_array[17] [31:0] $end
    $var wire 32 V reg_array[18] [31:0] $end
    $var wire 32 W reg_array[19] [31:0] $end
    $var wire 32 E reg_array[1] [31:0] $end
    $var wire 32 X reg_array[20] [31:0] $end
    $var wire 32 Y reg_array[21] [31:0] $end
    $var wire 32 Z reg_array[22] [31:0] $end
    $var wire 32 [ reg_array[23] [31:0] $end
    $var wire 32 \ reg_array[24] [31:0] $end
    $var wire 32 ] reg_array[25] [31:0] $end
    $var wire 32 ^ reg_array[26] [31:0] $end
    $var wire 32 _ reg_array[27] [31:0] $end
    $var wire 32 ` reg_array[28] [31:0] $end
    $var wire 32 a reg_array[29] [31:0] $end
    $var wire 32 F reg_array[2] [31:0] $end
    $var wire 32 b reg_array[30] [31:0] $end
    $var wire 32 c reg_array[31] [31:0] $end
    $var wire 32 G reg_array[3] [31:0] $end
    $var wire 32 H reg_array[4] [31:0] $end
    $var wire 32 I reg_array[5] [31:0] $end
    $var wire 32 J reg_array[6] [31:0] $end
    $var wire 32 K reg_array[7] [31:0] $end
    $var wire 32 L reg_array[8] [31:0] $end
    $var wire 32 M reg_array[9] [31:0] $end
   $upscope $end
   $scope module signextend $end
    $var wire 32 e Imm [31:0] $end
    $var wire 32 p ImmOp [31:0] $end
    $var wire  2 n ImmSrc [1:0] $end
   $upscope $end
  $upscope $end
 $upscope $end
$enddefinitions $end


#0
b00000000000000000000000000000000 #
b00000000000000000000000000000000 $
b00000000000000000000000000000000 %
b00000000000000000000000000000000 &
b00000000000000000000000000000000 '
b00000000000000000000000000000000 (
b00000000000000000000000000000000 )
b00000000000000000000000000000000 *
b00000000000000000000000000000000 +
b00000000000000000000000000000000 ,
b00000000000000000000000000000000 -
b00000000000000000000000000000000 .
b00000000000000000000000000000000 /
b00000000000000000000000000000000 0
b00000000000000000000000000000000 1
b00000000000000000000000000000000 2
b00000000000000000000000000000000 3
b00000000000000000000000000000000 4
b00000000000000000000000000000000 5
b00000000000000000000000000000000 6
b00000000000000000000000000000000 7
b00000000000000000000000000000000 8
b00000000000000000000000000000000 9
b00000000000000000000000000000000 :
b00000000000000000000000000000000 ;
b00000000000000000000000000000000 <
b00000000000000000000000000000000 =
b00000000000000000000000000000000 >
b00000000000000000000000000000000 ?
b00000000000000000000000000000000 @
b00000000000000000000000000000000 A
b00000000000000000000000000000000 B
b00000000000000000000000000000000 C
b00000000000000000000000000000000 D
b00000000000000000000000000000000 E
b00000000000000000000000000000000 F
b00000000000000000000000000000000 G
b00000000000000000000000000000000 H
b00000000000000000000000000000000 I
b00000000000000000000000000000000 J
b00000000000000000000000000000000 K
b00000000000000000000000000000000 L
b00000000000000000000000000000000 M
b00000000000000000000000000000000 N
b00000000000000000000000000000000 O
b00000000000000000000000000000000 P
b00000000000000000000000000000000 Q
b00000000000000000000000000000000 R
b00000000000000000000000000000000 S
b00000000000000000000000000000000 T
b00000000000000000000000000000000 U
b00000000000000000000000000000000 V
b00000000000000000000000000000000 W
b00000000000000000000000000000000 X
b00000000000000000000000000000000 Y
b00000000000000000000000000000000 Z
b00000000000000000000000000000000 [
b00000000000000000000000000000000 \
b00000000000000000000000000000000 ]
b00000000000000000000000000000000 ^
b00000000000000000000000000000000 _
b00000000000000000000000000000000 `
b00000000000000000000000000000000 a
b00000000000000000000000000000000 b
b00000000000000000000000000000000 c
b00000000000000000000000000000000 d
b00000000000000000000000000000000 e
b00000 f
b00000 g
b00000 h
0i
0j
0k
b000 l
1m
b00 n
1o
b00000000000000000000000000000000 p
b00000000000000000000000000000000 q
b00000000000000000000000000000000 r
b00000000000000000000000000000000 s
1t
b00000000000000000000000000000000 u
b00 v
b0000000 w
b000 x
0y
b000000000000000000000 z
b00000000000000000000000000000000 {
b00000000000000000000000000000100 |
b00000000000000000000000000000100 }
1~
1!!
b00000000000000000000000000000000 "!
b00000000000000000000000000000000 #!
b00000000000000000000000000000000 $!
b00000000000000000000000000000000 %!
b00000000000000000000000000000000 &!
b00000000000000000000000000000000 '!
b00000000000000000000000000000000 (!
b00000000000000000000000000000000 )!
b00000000000000000000000000000000 *!
b00000000000000000000000000000000 +!
b00000000000000000000000000000000 ,!
b00000000000000000000000000000000 -!
b00000000000000000000000000000000 .!
b00000000000000000000000000000000 /!
b00000000000000000000000000000000 0!
b00000000000000000000000000000000 1!
b00000000000000000000000000000000 2!
b00000000000000000000000000000000 3!
b00000000000000000000000000000000 4!
b00000000000000000000000000000000 5!
b00000000000000000000000000000000 6!
b00000000000000000000000000000000 7!
b00000000000000000000000000000000 8!
b00000000000000000000000000000000 9!
b00000000000000000000000000000000 :!
b00000000000000000000000000000000 ;!
b00000000000000000000000000000000 <!
b00000000000000000000000000000000 =!
b00000000000000000000000000000000 >!
b00000000000000000000000000000000 ?!
b00000000000000000000000000000000 @!
b00000000000000000000000000000000 A!
b00000000000000000000000000000000 B!
#1
b00111110100000000000000010010011 e
b01000 g
b00001 h
b00000000000000000000001111101000 p
b00000000000000000000001111101000 s
0t
b00000000000000000000001111101000 u
b0010011 w
b011111010000000000001 z
b00000000000000000000001111101000 {
0~
b00000000000000000000001111101000 B!
#2
b00000000000000000000001111101000 %
b00000000000000000000001111101000 E
1~
0!!
b00000000000000000000001111101000 #!
#3
0~
#4
b00000000000000000000000000000100 d
b01111101000000001000000100010011 e
b00001 f
b10000 g
b00010 h
b00000000000000000000011111010000 p
b00000000000000000000001111101000 q
b00000000000000000000101110111000 s
b00000000000000000000011111010000 u
1y
b011110100000000100010 z
b00000000000000000000011111010100 {
b00000000000000000000000000001000 |
b00000000000000000000000000001000 }
1~
b00000000000000000000101110111000 B!
#5
0~
#6
b00000000000000000000101110111000 &
b00000000000000000000101110111000 F
b00000000000000000000000000001000 d
b11000001100000010000000110010011 e
b00010 f
b11000 g
b00011 h
b11111111111111111111110000011000 p
b00000000000000000000101110111000 q
b00000000000000000000011111010000 s
b11111111111111111111110000011000 u
b100000110000001000011 z
b11111111111111111111110000100000 {
b00000000000000000000000000001100 |
b00000000000000000000000000001100 }
1~
b00000000000000000000101110111000 $!
b00000000000000000000011111010000 B!
#7
0~
#8
b00000000000000000000011111010000 '
b00000000000000000000011111010000 G
b00000000000000000000000000001100 d
b10000011000000011000001000010011 e
b00011 f
b10000 g
b00100 h
b11111111111111111111100000110000 p
b00000000000000000000011111010000 q
b00000000000000000000000000000000 s
1t
b11111111111111111111100000110000 u
0y
b100001100000001100100 z
b11111111111111111111100000111100 {
b00000000000000000000000000010000 |
b00000000000000000000000000010000 }
1~
b00000000000000000000011111010000 %!
b00000000000000000000000000000000 B!
#9
0~
#10
b00000000000000000000000000010000 d
b00111110100000100000001010010011 e
b00100 f
b01000 g
b00101 h
b00000000000000000000001111101000 p
b00000000000000000000000000000000 q
b00000000000000000000001111101000 s
0t
b00000000000000000000001111101000 u
b011111010000010000101 z
b00000000000000000000001111111000 {
b00000000000000000000000000010100 |
b00000000000000000000000000010100 }
1~
b00000000000000000000001111101000 B!
#11
0~
#12
b00000000000000000000001111101000 )
b00000000000000000000001111101000 I
b00000000000000000000000000010100 d
b00000000000000000000000000000000 e
b00000 f
b00000 g
b00000 h
b00000000000000000000000000000000 p
b00000000000000000000000000000000 s
1t
b00000000000000000000000000000000 u
b0000000 w
b000000000000000000000 z
b00000000000000000000000000010100 {
b00000000000000000000000000011000 |
b00000000000000000000000000011000 }
1~
b00000000000000000000001111101000 '!
b00000000000000000000000000000000 B!
#13
0~
#14
b00000000000000000000000000011000 d
b00000000000000000000000000011000 {
b00000000000000000000000000011100 |
b00000000000000000000000000011100 }
1~
#15
0~
#16
b00000000000000000000000000011100 d
b00000000000000000000000000011100 {
b00000000000000000000000000100000 |
b00000000000000000000000000100000 }
1~
#17
0~
#18
b00000000000000000000000000100000 d
b00000000000000000000000000100000 {
b00000000000000000000000000100100 |
b00000000000000000000000000100100 }
1~
#19
0~
#20
b00000000000000000000000000100100 d
b00000000000000000000000000100100 {
b00000000000000000000000000101000 |
b00000000000000000000000000101000 }
1~
#21
0~
#22
b00000000000000000000000000101000 d
b00000000000000000000000000101000 {
b00000000000000000000000000101100 |
b00000000000000000000000000101100 }
1~
#23
0~
#24
b00000000000000000000000000101100 d
b00000000000000000000000000101100 {
b00000000000000000000000000110000 |
b00000000000000000000000000110000 }
1~
#25
0~
#26
b00000000000000000000000000110000 d
b00000000000000000000000000110000 {
b00000000000000000000000000110100 |
b00000000000000000000000000110100 }
1~
#27
0~
#28
b00000000000000000000000000110100 d
b00000000000000000000000000110100 {
b00000000000000000000000000111000 |
b00000000000000000000000000111000 }
1~
#29
0~
#30
b00000000000000000000000000111000 d
b00000000000000000000000000111000 {
b00000000000000000000000000111100 |
b00000000000000000000000000111100 }
1~
#31
0~
#32
b00000000000000000000000000111100 d
b00000000000000000000000000111100 {
b00000000000000000000000001000000 |
b00000000000000000000000001000000 }
1~
#33
0~
#34
b00000000000000000000000001000000 d
b00000000000000000000000001000000 {
b00000000000000000000000001000100 |
b00000000000000000000000001000100 }
1~
#35
0~
#36
b00000000000000000000000001000100 d
b00000000000000000000000001000100 {
b00000000000000000000000001001000 |
b00000000000000000000000001001000 }
1~
#37
0~
#38
b00000000000000000000000001001000 d
b00000000000000000000000001001000 {
b00000000000000000000000001001100 |
b00000000000000000000000001001100 }
1~
#39
0~
#40
b00000000000000000000000001001100 d
b00000000000000000000000001001100 {
b00000000000000000000000001010000 |
b00000000000000000000000001010000 }
1~
#41
0~
#42
b00000000000000000000000001010000 d
b00000000000000000000000001010000 {
b00000000000000000000000001010100 |
b00000000000000000000000001010100 }
1~
#43
0~
#44
b00000000000000000000000001010100 d
b00000000000000000000000001010100 {
b00000000000000000000000001011000 |
b00000000000000000000000001011000 }
1~
#45
0~
#46
b00000000000000000000000001011000 d
b00000000000000000000000001011000 {
b00000000000000000000000001011100 |
b00000000000000000000000001011100 }
1~
#47
0~
#48
b00000000000000000000000001011100 d
b00000000000000000000000001011100 {
b00000000000000000000000001100000 |
b00000000000000000000000001100000 }
1~
#49
0~
#50
b00000000000000000000000001100000 d
b00000000000000000000000001100000 {
b00000000000000000000000001100100 |
b00000000000000000000000001100100 }
1~
#51
0~
#52
b00000000000000000000000001100100 d
b00000000000000000000000001100100 {
b00000000000000000000000001101000 |
b00000000000000000000000001101000 }
1~
#53
0~
#54
b00000000000000000000000001101000 d
b00000000000000000000000001101000 {
b00000000000000000000000001101100 |
b00000000000000000000000001101100 }
1~
#55
0~
#56
b00000000000000000000000001101100 d
b00000000000000000000000001101100 {
b00000000000000000000000001110000 |
b00000000000000000000000001110000 }
1~
#57
0~
#58
b00000000000000000000000001110000 d
b00000000000000000000000001110000 {
b00000000000000000000000001110100 |
b00000000000000000000000001110100 }
1~
#59
0~
#60
b00000000000000000000000001110100 d
b00000000000000000000000001110100 {
b00000000000000000000000001111000 |
b00000000000000000000000001111000 }
1~
#61
0~
#62
b00000000000000000000000001111000 d
b00000000000000000000000001111000 {
b00000000000000000000000001111100 |
b00000000000000000000000001111100 }
1~
#63
0~
#64
b00000000000000000000000001111100 d
b00000000000000000000000001111100 {
b00000000000000000000000010000000 |
b00000000000000000000000010000000 }
1~
#65
0~
#66
b00000000000000000000000010000000 d
b00000000000000000000000010000000 {
b00000000000000000000000010000100 |
b00000000000000000000000010000100 }
1~
#67
0~
#68
b00000000000000000000000010000100 d
b00000000000000000000000010000100 {
b00000000000000000000000010001000 |
b00000000000000000000000010001000 }
1~
#69
0~
#70
b00000000000000000000000010001000 d
b00000000000000000000000010001000 {
b00000000000000000000000010001100 |
b00000000000000000000000010001100 }
1~
#71
0~
#72
b00000000000000000000000010001100 d
b00000000000000000000000010001100 {
b00000000000000000000000010010000 |
b00000000000000000000000010010000 }
1~
#73
0~
#74
b00000000000000000000000010010000 d
b00000000000000000000000010010000 {
b00000000000000000000000010010100 |
b00000000000000000000000010010100 }
1~
#75
0~
#76
b00000000000000000000000010010100 d
b00000000000000000000000010010100 {
b00000000000000000000000010011000 |
b00000000000000000000000010011000 }
1~
#77
0~
#78
b00000000000000000000000010011000 d
b00000000000000000000000010011000 {
b00000000000000000000000010011100 |
b00000000000000000000000010011100 }
1~
#79
0~
#80
b00000000000000000000000010011100 d
b00000000000000000000000010011100 {
b00000000000000000000000010100000 |
b00000000000000000000000010100000 }
1~
#81
0~
#82
b00000000000000000000000010100000 d
b00000000000000000000000010100000 {
b00000000000000000000000010100100 |
b00000000000000000000000010100100 }
1~
#83
0~
#84
b00000000000000000000000010100100 d
b00000000000000000000000010100100 {
b00000000000000000000000010101000 |
b00000000000000000000000010101000 }
1~
#85
0~
#86
b00000000000000000000000010101000 d
b00000000000000000000000010101000 {
b00000000000000000000000010101100 |
b00000000000000000000000010101100 }
1~
#87
0~
#88
b00000000000000000000000010101100 d
b00000000000000000000000010101100 {
b00000000000000000000000010110000 |
b00000000000000000000000010110000 }
1~
#89
0~
#90
b00000000000000000000000010110000 d
b00000000000000000000000010110000 {
b00000000000000000000000010110100 |
b00000000000000000000000010110100 }
1~
#91
0~
#92
b00000000000000000000000010110100 d
b00000000000000000000000010110100 {
b00000000000000000000000010111000 |
b00000000000000000000000010111000 }
1~
#93
0~
#94
b00000000000000000000000010111000 d
b00000000000000000000000010111000 {
b00000000000000000000000010111100 |
b00000000000000000000000010111100 }
1~
#95
0~
#96
b00000000000000000000000010111100 d
b00000000000000000000000010111100 {
b00000000000000000000000011000000 |
b00000000000000000000000011000000 }
1~
#97
0~
#98
b00000000000000000000000011000000 d
b00000000000000000000000011000000 {
b00000000000000000000000011000100 |
b00000000000000000000000011000100 }
1~
#99
0~
#100
b00000000000000000000000011000100 d
b00000000000000000000000011000100 {
b00000000000000000000000011001000 |
b00000000000000000000000011001000 }
1~
#101
0~
#102
b00000000000000000000000011001000 d
b00000000000000000000000011001000 {
b00000000000000000000000011001100 |
b00000000000000000000000011001100 }
1~
#103
0~
#104
b00000000000000000000000011001100 d
b00000000000000000000000011001100 {
b00000000000000000000000011010000 |
b00000000000000000000000011010000 }
1~
#105
0~
#106
b00000000000000000000000011010000 d
b00000000000000000000000011010000 {
b00000000000000000000000011010100 |
b00000000000000000000000011010100 }
1~
#107
0~
#108
b00000000000000000000000011010100 d
b00000000000000000000000011010100 {
b00000000000000000000000011011000 |
b00000000000000000000000011011000 }
1~
#109
0~
#110
b00000000000000000000000011011000 d
b00000000000000000000000011011000 {
b00000000000000000000000011011100 |
b00000000000000000000000011011100 }
1~
#111
0~
#112
b00000000000000000000000011011100 d
b00000000000000000000000011011100 {
b00000000000000000000000011100000 |
b00000000000000000000000011100000 }
1~
#113
0~
