Task4/ProgramCounter/pc.sv
module pc (
    input logic [31:0] ImmOp,
    input logic        clk,
    input logic        rst,
    input logic        PCsrc,
    output logic [31:0] PC_out
);

logic [31:0] branch_PC;
logic [31:0] inc_PC; 
logic [31:0] next_PC;

assign branch_PC = PC_out + ImmOp;
assign inc_PC    = PC_out + 32'b100;
assign next_PC   = PCsrc ? branch_PC : inc_PC;

always_ff @(posedge clk, posedge rst) 
    if (rst) PC_out <= 32'b0;
    else     PC_out <= next_PC;

endmodule

Task4/pc.vcd
$version Generated by VerilatedVcd $end
$date Tue Dec  6 21:18:02 2022 $end
$timescale 1ps $end

 $scope module TOP $end
  $var wire 32 # ImmOp [31:0] $end
  $var wire 32 ' PC_out [31:0] $end
  $var wire  1 & PCsrc $end
  $var wire  1 $ clk $end
  $var wire  1 % rst $end
  $scope module pc $end
   $var wire 32 # ImmOp [31:0] $end
   $var wire 32 ' PC_out [31:0] $end
   $var wire  1 & PCsrc $end
   $var wire 32 ( branch_PC [31:0] $end
   $var wire  1 $ clk $end
   $var wire 32 ) inc_PC [31:0] $end
   $var wire 32 * next_PC [31:0] $end
   $var wire  1 % rst $end
  $upscope $end
 $upscope $end
$enddefinitions $end


#0
b00000000000000000000000000000000 #
1$
1%
0&
b00000000000000000000000000000000 '
b00000000000000000000000000000000 (
b00000000000000000000000000000100 )
b00000000000000000000000000000100 *
#1
0$
#2
1$
0%
#3
0$
#4
1$
b00000000000000000000000000000100 '
b00000000000000000000000000000100 (
b00000000000000000000000000001000 )
b00000000000000000000000000001000 *
#5
0$
#6
1$
b00000000000000000000000000001000 '
b00000000000000000000000000001000 (
b00000000000000000000000000001100 )
b00000000000000000000000000001100 *
#7
0$
#8
1$
b00000000000000000000000000001100 '
b00000000000000000000000000001100 (
b00000000000000000000000000010000 )
b00000000000000000000000000010000 *
#9
0$
#10
1$
b00000000000000000000000000010000 '
b00000000000000000000000000010000 (
b00000000000000000000000000010100 )
b00000000000000000000000000010100 *
#11
0$
#12
1$
b00000000000000000000000000010100 '
b00000000000000000000000000010100 (
b00000000000000000000000000011000 )
b00000000000000000000000000011000 *
#13
0$
#14
1$
b00000000000000000000000000011000 '
b00000000000000000000000000011000 (
b00000000000000000000000000011100 )
b00000000000000000000000000011100 *
#15
0$
#16
1$
b00000000000000000000000000011100 '
b00000000000000000000000000011100 (
b00000000000000000000000000100000 )
b00000000000000000000000000100000 *
#17
0$
#18
1$
b00000000000000000000000000100000 '
b00000000000000000000000000100000 (
b00000000000000000000000000100100 )
b00000000000000000000000000100100 *
#19
0$
#20
1$
b00000000000000000000000000100100 '
b00000000000000000000000000100100 (
b00000000000000000000000000101000 )
b00000000000000000000000000101000 *
#21
0$
#22
1$
1%
b00000000000000000000000000101000 '
b00000000000000000000000000101000 (
b00000000000000000000000000101100 )
b00000000000000000000000000101100 *
#23
0$
b00000000000000000000000000000000 '
b00000000000000000000000000000000 (
b00000000000000000000000000000100 )
b00000000000000000000000000000100 *
#24
1$
0%
#25
0$
#26
1$
b00000000000000000000000000000100 '
b00000000000000000000000000000100 (
b00000000000000000000000000001000 )
b00000000000000000000000000001000 *
#27
0$
#28
1$
b00000000000000000000000000001000 '
b00000000000000000000000000001000 (
b00000000000000000000000000001100 )
b00000000000000000000000000001100 *
#29
0$
#30
1$
b00000000000000000000000000001100 '
b00000000000000000000000000001100 (
b00000000000000000000000000010000 )
b00000000000000000000000000010000 *
#31
0$
#32
1$
b00000000000000000000000000010000 '
b00000000000000000000000000010000 (
b00000000000000000000000000010100 )
b00000000000000000000000000010100 *
#33
0$
#34
1$
b00000000000000000000000000010100 '
b00000000000000000000000000010100 (
b00000000000000000000000000011000 )
b00000000000000000000000000011000 *
#35
0$
#36
1$
b00000000000000000000000000011000 '
b00000000000000000000000000011000 (
b00000000000000000000000000011100 )
b00000000000000000000000000011100 *
#37
0$
#38
1$
b00000000000000000000000000011100 '
b00000000000000000000000000011100 (
b00000000000000000000000000100000 )
b00000000000000000000000000100000 *
#39
0$
#40
1$
b00000000000000000000000000100000 '
b00000000000000000000000000100000 (
b00000000000000000000000000100100 )
b00000000000000000000000000100100 *
#41
0$
#42
1$
b00000000000000000000000000100100 '
b00000000000000000000000000100100 (
b00000000000000000000000000101000 )
b00000000000000000000000000101000 *
#43
0$
#44
1$
b00000000000000000000000000101000 '
b00000000000000000000000000101000 (
b00000000000000000000000000101100 )
b00000000000000000000000000101100 *
#45
0$
#46
1$
b00000000000000000000000000101100 '
b00000000000000000000000000101100 (
b00000000000000000000000000110000 )
b00000000000000000000000000110000 *
#47
0$
#48
1$
b00000000000000000000000000110000 '
b00000000000000000000000000110000 (
b00000000000000000000000000110100 )
b00000000000000000000000000110100 *
#49
0$
#50
1$
b00000000000000000000000000110100 '
b00000000000000000000000000110100 (
b00000000000000000000000000111000 )
b00000000000000000000000000111000 *
#51
0$
#52
1$
b00000000000000000000000000111000 '
b00000000000000000000000000111000 (
b00000000000000000000000000111100 )
b00000000000000000000000000111100 *
#53
0$
#54
1$
b00000000000000000000000000111100 '
b00000000000000000000000000111100 (
b00000000000000000000000001000000 )
b00000000000000000000000001000000 *
#55
0$
#56
1$
b00000000000000000000000001000000 '
b00000000000000000000000001000000 (
b00000000000000000000000001000100 )
b00000000000000000000000001000100 *
#57
0$
#58
1$
b00000000000000000000000001000100 '
b00000000000000000000000001000100 (
b00000000000000000000000001001000 )
b00000000000000000000000001001000 *
#59
0$
#60
1$
b00000000000000000000000001001000 '
b00000000000000000000000001001000 (
b00000000000000000000000001001100 )
b00000000000000000000000001001100 *
#61
0$
#62
1$
b00000000000000000000000001001100 '
b00000000000000000000000001001100 (
b00000000000000000000000001010000 )
b00000000000000000000000001010000 *
#63
0$
#64
1$
b00000000000000000000000001010000 '
b00000000000000000000000001010000 (
b00000000000000000000000001010100 )
b00000000000000000000000001010100 *
#65
0$
#66
1$
b00000000000000000000000001010100 '
b00000000000000000000000001010100 (
b00000000000000000000000001011000 )
b00000000000000000000000001011000 *
#67
0$
#68
1$
b00000000000000000000000001011000 '
b00000000000000000000000001011000 (
b00000000000000000000000001011100 )
b00000000000000000000000001011100 *
#69
0$
#70
1$
b00000000000000000000000001011100 '
b00000000000000000000000001011100 (
b00000000000000000000000001100000 )
b00000000000000000000000001100000 *
#71
0$
#72
1$
b00000000000000000000000001100000 '
b00000000000000000000000001100000 (
b00000000000000000000000001100100 )
b00000000000000000000000001100100 *
#73
0$
#74
1$
b00000000000000000000000001100100 '
b00000000000000000000000001100100 (
b00000000000000000000000001101000 )
b00000000000000000000000001101000 *
#75
0$
#76
1$
b00000000000000000000000001101000 '
b00000000000000000000000001101000 (
b00000000000000000000000001101100 )
b00000000000000000000000001101100 *
#77
0$
#78
1$
b00000000000000000000000001101100 '
b00000000000000000000000001101100 (
b00000000000000000000000001110000 )
b00000000000000000000000001110000 *
#79
0$
#80
1$
b00000000000000000000000001110000 '
b00000000000000000000000001110000 (
b00000000000000000000000001110100 )
b00000000000000000000000001110100 *
#81
0$
#82
1$
b00000000000000000000000001110100 '
b00000000000000000000000001110100 (
b00000000000000000000000001111000 )
b00000000000000000000000001111000 *
#83
0$
#84
1$
b00000000000000000000000001111000 '
b00000000000000000000000001111000 (
b00000000000000000000000001111100 )
b00000000000000000000000001111100 *
#85
0$
#86
1$
b00000000000000000000000001111100 '
b00000000000000000000000001111100 (
b00000000000000000000000010000000 )
b00000000000000000000000010000000 *
#87
0$
#88
1$
b00000000000000000000000010000000 '
b00000000000000000000000010000000 (
b00000000000000000000000010000100 )
b00000000000000000000000010000100 *
#89
0$
#90
1$
b00000000000000000000000010000100 '
b00000000000000000000000010000100 (
b00000000000000000000000010001000 )
b00000000000000000000000010001000 *
#91
0$
#92
1$
b00000000000000000000000010001000 '
b00000000000000000000000010001000 (
b00000000000000000000000010001100 )
b00000000000000000000000010001100 *
#93
0$
#94
1$
b00000000000000000000000010001100 '
b00000000000000000000000010001100 (
b00000000000000000000000010010000 )
b00000000000000000000000010010000 *
#95
0$
#96
1$
b00000000000000000000000010010000 '
b00000000000000000000000010010000 (
b00000000000000000000000010010100 )
b00000000000000000000000010010100 *
#97
0$
#98
1$
b00000000000000000000000010010100 '
b00000000000000000000000010010100 (
b00000000000000000000000010011000 )
b00000000000000000000000010011000 *
#99
0$
#100
1$
b00000000000000000000000010011000 '
b00000000000000000000000010011000 (
b00000000000000000000000010011100 )
b00000000000000000000000010011100 *
#101
0$
#102
1$
b00000000000000000000000010011100 '
b00000000000000000000000010011100 (
b00000000000000000000000010100000 )
b00000000000000000000000010100000 *
#103
0$
#104
1$
b00000000000000000000000010100000 '
b00000000000000000000000010100000 (
b00000000000000000000000010100100 )
b00000000000000000000000010100100 *
#105
0$
#106
1$
b00000000000000000000000010100100 '
b00000000000000000000000010100100 (
b00000000000000000000000010101000 )
b00000000000000000000000010101000 *
#107
0$
#108
1$
b00000000000000000000000010101000 '
b00000000000000000000000010101000 (
b00000000000000000000000010101100 )
b00000000000000000000000010101100 *
#109
0$
#110
1$
b00000000000000000000000010101100 '
b00000000000000000000000010101100 (
b00000000000000000000000010110000 )
b00000000000000000000000010110000 *
#111
0$
#112
1$
b00000000000000000000000010110000 '
b00000000000000000000000010110000 (
b00000000000000000000000010110100 )
b00000000000000000000000010110100 *
#113
0$
#114
1$
b00000000000000000000000010110100 '
b00000000000000000000000010110100 (
b00000000000000000000000010111000 )
b00000000000000000000000010111000 *
#115
0$
#116
1$
b00000000000000000000000010111000 '
b00000000000000000000000010111000 (
b00000000000000000000000010111100 )
b00000000000000000000000010111100 *
#117
0$
#118
1$
b00000000000000000000000010111100 '
b00000000000000000000000010111100 (
b00000000000000000000000011000000 )
b00000000000000000000000011000000 *
#119
0$
#120
1$
b00000000000000000000000011000000 '
b00000000000000000000000011000000 (
b00000000000000000000000011000100 )
b00000000000000000000000011000100 *
#121
0$
#122
1$
b00000000000000000000000011000100 '
b00000000000000000000000011000100 (
b00000000000000000000000011001000 )
b00000000000000000000000011001000 *
#123
0$
#124
1$
b00000000000000000000000011001000 '
b00000000000000000000000011001000 (
b00000000000000000000000011001100 )
b00000000000000000000000011001100 *
#125
0$
#126
1$
b00000000000000000000000011001100 '
b00000000000000000000000011001100 (
b00000000000000000000000011010000 )
b00000000000000000000000011010000 *
#127
0$
#128
1$
b00000000000000000000000011010000 '
b00000000000000000000000011010000 (
b00000000000000000000000011010100 )
b00000000000000000000000011010100 *
#129
0$
#130
1$
b00000000000000000000000011010100 '
b00000000000000000000000011010100 (
b00000000000000000000000011011000 )
b00000000000000000000000011011000 *
#131
0$
#132
1$
b00000000000000000000000011011000 '
b00000000000000000000000011011000 (
b00000000000000000000000011011100 )
b00000000000000000000000011011100 *
#133
0$
#134
1$
b00000000000000000000000011011100 '
b00000000000000000000000011011100 (
b00000000000000000000000011100000 )
b00000000000000000000000011100000 *
#135
0$
#136
1$
b00000000000000000000000011100000 '
b00000000000000000000000011100000 (
b00000000000000000000000011100100 )
b00000000000000000000000011100100 *
#137
0$
#138
1$
b00000000000000000000000011100100 '
b00000000000000000000000011100100 (
b00000000000000000000000011101000 )
b00000000000000000000000011101000 *
#139
0$
#140
1$
b00000000000000000000000011101000 '
b00000000000000000000000011101000 (
b00000000000000000000000011101100 )
b00000000000000000000000011101100 *
#141
0$
#142
1$
b00000000000000000000000011101100 '
b00000000000000000000000011101100 (
b00000000000000000000000011110000 )
b00000000000000000000000011110000 *
#143
0$
#144
1$
b00000000000000000000000011110000 '
b00000000000000000000000011110000 (
b00000000000000000000000011110100 )
b00000000000000000000000011110100 *
#145
0$
#146
1$
b00000000000000000000000011110100 '
b00000000000000000000000011110100 (
b00000000000000000000000011111000 )
b00000000000000000000000011111000 *
#147
0$
#148
1$
b00000000000000000000000011111000 '
b00000000000000000000000011111000 (
b00000000000000000000000011111100 )
b00000000000000000000000011111100 *
#149
0$
#150
1$
b00000000000000000000000011111100 '
b00000000000000000000000011111100 (
b00000000000000000000000100000000 )
b00000000000000000000000100000000 *
#151
0$
#152
1$
b00000000000000000000000100000000 '
b00000000000000000000000100000000 (
b00000000000000000000000100000100 )
b00000000000000000000000100000100 *
#153
0$
#154
1$
b00000000000000000000000100000100 '
b00000000000000000000000100000100 (
b00000000000000000000000100001000 )
b00000000000000000000000100001000 *
#155
0$
#156
1$
b00000000000000000000000100001000 '
b00000000000000000000000100001000 (
b00000000000000000000000100001100 )
b00000000000000000000000100001100 *
#157
0$
#158
1$
b00000000000000000000000100001100 '
b00000000000000000000000100001100 (
b00000000000000000000000100010000 )
b00000000000000000000000100010000 *
#159
0$
#160
1$
b00000000000000000000000100010000 '
b00000000000000000000000100010000 (
b00000000000000000000000100010100 )
b00000000000000000000000100010100 *
#161
0$
#162
1$
b00000000000000000000000100010100 '
b00000000000000000000000100010100 (
b00000000000000000000000100011000 )
b00000000000000000000000100011000 *
#163
0$
#164
1$
b00000000000000000000000100011000 '
b00000000000000000000000100011000 (
b00000000000000000000000100011100 )
b00000000000000000000000100011100 *
#165
0$
#166
1$
b00000000000000000000000100011100 '
b00000000000000000000000100011100 (
b00000000000000000000000100100000 )
b00000000000000000000000100100000 *
#167
0$
#168
1$
b00000000000000000000000100100000 '
b00000000000000000000000100100000 (
b00000000000000000000000100100100 )
b00000000000000000000000100100100 *
#169
0$
#170
1$
b00000000000000000000000100100100 '
b00000000000000000000000100100100 (
b00000000000000000000000100101000 )
b00000000000000000000000100101000 *
#171
0$
#172
1$
b00000000000000000000000100101000 '
b00000000000000000000000100101000 (
b00000000000000000000000100101100 )
b00000000000000000000000100101100 *
#173
0$
#174
1$
b00000000000000000000000100101100 '
b00000000000000000000000100101100 (
b00000000000000000000000100110000 )
b00000000000000000000000100110000 *
#175
0$
#176
1$
b00000000000000000000000100110000 '
b00000000000000000000000100110000 (
b00000000000000000000000100110100 )
b00000000000000000000000100110100 *
#177
0$
#178
1$
b00000000000000000000000100110100 '
b00000000000000000000000100110100 (
b00000000000000000000000100111000 )
b00000000000000000000000100111000 *
#179
0$
#180
1$
b00000000000000000000000100111000 '
b00000000000000000000000100111000 (
b00000000000000000000000100111100 )
b00000000000000000000000100111100 *
#181
0$
#182
1$
b00000000000000000000000100111100 '
b00000000000000000000000100111100 (
b00000000000000000000000101000000 )
b00000000000000000000000101000000 *
#183
0$
#184
1$
b00000000000000000000000101000000 '
b00000000000000000000000101000000 (
b00000000000000000000000101000100 )
b00000000000000000000000101000100 *
#185
0$
#186
1$
b00000000000000000000000101000100 '
b00000000000000000000000101000100 (
b00000000000000000000000101001000 )
b00000000000000000000000101001000 *
#187
0$
#188
1$
b00000000000000000000000101001000 '
b00000000000000000000000101001000 (
b00000000000000000000000101001100 )
b00000000000000000000000101001100 *
#189
0$
#190
1$
b00000000000000000000000101001100 '
b00000000000000000000000101001100 (
b00000000000000000000000101010000 )
b00000000000000000000000101010000 *
#191
0$
#192
1$
b00000000000000000000000101010000 '
b00000000000000000000000101010000 (
b00000000000000000000000101010100 )
b00000000000000000000000101010100 *
#193
0$
#194
1$
b00000000000000000000000101010100 '
b00000000000000000000000101010100 (
b00000000000000000000000101011000 )
b00000000000000000000000101011000 *
#195
0$
#196
1$
b00000000000000000000000101011000 '
b00000000000000000000000101011000 (
b00000000000000000000000101011100 )
b00000000000000000000000101011100 *
#197
0$
#198
1$
b00000000000000000000000101011100 '
b00000000000000000000000101011100 (
b00000000000000000000000101100000 )
b00000000000000000000000101100000 *
#199
0$
#200
1$
b00000000000000000000000101100000 '
b00000000000000000000000101100000 (
b00000000000000000000000101100100 )
b00000000000000000000000101100100 *
#201
0$
#202
1$
b00000000000000000000000101100100 '
b00000000000000000000000101100100 (
b00000000000000000000000101101000 )
b00000000000000000000000101101000 *
#203
0$
#204
1$
b00000000000000000000000101101000 '
b00000000000000000000000101101000 (
b00000000000000000000000101101100 )
b00000000000000000000000101101100 *
#205
0$
#206
1$
b00000000000000000000000101101100 '
b00000000000000000000000101101100 (
b00000000000000000000000101110000 )
b00000000000000000000000101110000 *
#207
0$
#208
1$
b00000000000000000000000101110000 '
b00000000000000000000000101110000 (
b00000000000000000000000101110100 )
b00000000000000000000000101110100 *
#209
0$
#210
1$
b00000000000000000000000101110100 '
b00000000000000000000000101110100 (
b00000000000000000000000101111000 )
b00000000000000000000000101111000 *
#211
0$
#212
1$
b00000000000000000000000101111000 '
b00000000000000000000000101111000 (
b00000000000000000000000101111100 )
b00000000000000000000000101111100 *
#213
0$
#214
1$
b00000000000000000000000101111100 '
b00000000000000000000000101111100 (
b00000000000000000000000110000000 )
b00000000000000000000000110000000 *
#215
0$
#216
1$
b00000000000000000000000110000000 '
b00000000000000000000000110000000 (
b00000000000000000000000110000100 )
b00000000000000000000000110000100 *
#217
0$
#218
1$
b00000000000000000000000110000100 '
b00000000000000000000000110000100 (
b00000000000000000000000110001000 )
b00000000000000000000000110001000 *
#219
0$
#220
1$
b00000000000000000000000110001000 '
b00000000000000000000000110001000 (
b00000000000000000000000110001100 )
b00000000000000000000000110001100 *
#221
0$
#222
1$
b00000000000000000000000110001100 '
b00000000000000000000000110001100 (
b00000000000000000000000110010000 )
b00000000000000000000000110010000 *
#223
0$
#224
1$
b00000000000000000000000110010000 '
b00000000000000000000000110010000 (
b00000000000000000000000110010100 )
b00000000000000000000000110010100 *
#225
0$
#226
1$
b00000000000000000000000110010100 '
b00000000000000000000000110010100 (
b00000000000000000000000110011000 )
b00000000000000000000000110011000 *
#227
0$
#228
1$
b00000000000000000000000110011000 '
b00000000000000000000000110011000 (
b00000000000000000000000110011100 )
b00000000000000000000000110011100 *
#229
0$
#230
1$
b00000000000000000000000110011100 '
b00000000000000000000000110011100 (
b00000000000000000000000110100000 )
b00000000000000000000000110100000 *
#231
0$
#232
1$
b00000000000000000000000110100000 '
b00000000000000000000000110100000 (
b00000000000000000000000110100100 )
b00000000000000000000000110100100 *
#233
0$
#234
1$
b00000000000000000000000110100100 '
b00000000000000000000000110100100 (
b00000000000000000000000110101000 )
b00000000000000000000000110101000 *
#235
0$
#236
1$
b00000000000000000000000110101000 '
b00000000000000000000000110101000 (
b00000000000000000000000110101100 )
b00000000000000000000000110101100 *
#237
0$
#238
1$
b00000000000000000000000110101100 '
b00000000000000000000000110101100 (
b00000000000000000000000110110000 )
b00000000000000000000000110110000 *
#239
0$
#240
1$
b00000000000000000000000110110000 '
b00000000000000000000000110110000 (
b00000000000000000000000110110100 )
b00000000000000000000000110110100 *
#241
0$
#242
1$
b00000000000000000000000110110100 '
b00000000000000000000000110110100 (
b00000000000000000000000110111000 )
b00000000000000000000000110111000 *
#243
0$
#244
1$
b00000000000000000000000110111000 '
b00000000000000000000000110111000 (
b00000000000000000000000110111100 )
b00000000000000000000000110111100 *
#245
0$
#246
1$
b00000000000000000000000110111100 '
b00000000000000000000000110111100 (
b00000000000000000000000111000000 )
b00000000000000000000000111000000 *
#247
0$
#248
1$
b00000000000000000000000111000000 '
b00000000000000000000000111000000 (
b00000000000000000000000111000100 )
b00000000000000000000000111000100 *
#249
0$
#250
1$
b00000000000000000000000111000100 '
b00000000000000000000000111000100 (
b00000000000000000000000111001000 )
b00000000000000000000000111001000 *
#251
0$
#252
1$
b00000000000000000000000111001000 '
b00000000000000000000000111001000 (
b00000000000000000000000111001100 )
b00000000000000000000000111001100 *
#253
0$
#254
1$
b00000000000000000000000111001100 '
b00000000000000000000000111001100 (
b00000000000000000000000111010000 )
b00000000000000000000000111010000 *
#255
0$
#256
1$
b00000000000000000000000111010000 '
b00000000000000000000000111010000 (
b00000000000000000000000111010100 )
b00000000000000000000000111010100 *
#257
0$
#258
1$
b00000000000000000000000111010100 '
b00000000000000000000000111010100 (
b00000000000000000000000111011000 )
b00000000000000000000000111011000 *
#259
0$
#260
1$
b00000000000000000000000111011000 '
b00000000000000000000000111011000 (
b00000000000000000000000111011100 )
b00000000000000000000000111011100 *
#261
0$
#262
1$
b00000000000000000000000111011100 '
b00000000000000000000000111011100 (
b00000000000000000000000111100000 )
b00000000000000000000000111100000 *
#263
0$
#264
1$
b00000000000000000000000111100000 '
b00000000000000000000000111100000 (
b00000000000000000000000111100100 )
b00000000000000000000000111100100 *
#265
0$
#266
1$
b00000000000000000000000111100100 '
b00000000000000000000000111100100 (
b00000000000000000000000111101000 )
b00000000000000000000000111101000 *
#267
0$
#268
1$
b00000000000000000000000111101000 '
b00000000000000000000000111101000 (
b00000000000000000000000111101100 )
b00000000000000000000000111101100 *
#269
0$
#270
1$
b00000000000000000000000111101100 '
b00000000000000000000000111101100 (
b00000000000000000000000111110000 )
b00000000000000000000000111110000 *
#271
0$
#272
1$
b00000000000000000000000111110000 '
b00000000000000000000000111110000 (
b00000000000000000000000111110100 )
b00000000000000000000000111110100 *
#273
0$
#274
1$
b00000000000000000000000111110100 '
b00000000000000000000000111110100 (
b00000000000000000000000111111000 )
b00000000000000000000000111111000 *
#275
0$
#276
1$
b00000000000000000000000111111000 '
b00000000000000000000000111111000 (
b00000000000000000000000111111100 )
b00000000000000000000000111111100 *
#277
0$
#278
1$
b00000000000000000000000111111100 '
b00000000000000000000000111111100 (
b00000000000000000000001000000000 )
b00000000000000000000001000000000 *
#279
0$
#280
1$
b00000000000000000000001000000000 '
b00000000000000000000001000000000 (
b00000000000000000000001000000100 )
b00000000000000000000001000000100 *
#281
0$
#282
1$
b00000000000000000000001000000100 '
b00000000000000000000001000000100 (
b00000000000000000000001000001000 )
b00000000000000000000001000001000 *
#283
0$
#284
1$
b00000000000000000000001000001000 '
b00000000000000000000001000001000 (
b00000000000000000000001000001100 )
b00000000000000000000001000001100 *
#285
0$
#286
1$
b00000000000000000000001000001100 '
b00000000000000000000001000001100 (
b00000000000000000000001000010000 )
b00000000000000000000001000010000 *
#287
0$
#288
1$
b00000000000000000000001000010000 '
b00000000000000000000001000010000 (
b00000000000000000000001000010100 )
b00000000000000000000001000010100 *
#289
0$
#290
1$
b00000000000000000000001000010100 '
b00000000000000000000001000010100 (
b00000000000000000000001000011000 )
b00000000000000000000001000011000 *
#291
0$
#292
1$
b00000000000000000000001000011000 '
b00000000000000000000001000011000 (
b00000000000000000000001000011100 )
b00000000000000000000001000011100 *
#293
0$
#294
1$
b00000000000000000000001000011100 '
b00000000000000000000001000011100 (
b00000000000000000000001000100000 )
b00000000000000000000001000100000 *
#295
0$
#296
1$
b00000000000000000000001000100000 '
b00000000000000000000001000100000 (
b00000000000000000000001000100100 )
b00000000000000000000001000100100 *
#297
0$
#298
1$
b00000000000000000000001000100100 '
b00000000000000000000001000100100 (
b00000000000000000000001000101000 )
b00000000000000000000001000101000 *
#299
0$
#300
1$
b00000000000000000000001000101000 '
b00000000000000000000001000101000 (
b00000000000000000000001000101100 )
b00000000000000000000001000101100 *
#301
0$
#302
1$
b00000000000000000000001000101100 '
b00000000000000000000001000101100 (
b00000000000000000000001000110000 )
b00000000000000000000001000110000 *
#303
0$
#304
1$
b00000000000000000000001000110000 '
b00000000000000000000001000110000 (
b00000000000000000000001000110100 )
b00000000000000000000001000110100 *
#305
0$
#306
1$
b00000000000000000000001000110100 '
b00000000000000000000001000110100 (
b00000000000000000000001000111000 )
b00000000000000000000001000111000 *
#307
0$
#308
1$
b00000000000000000000001000111000 '
b00000000000000000000001000111000 (
b00000000000000000000001000111100 )
b00000000000000000000001000111100 *
#309
0$
#310
1$
b00000000000000000000001000111100 '
b00000000000000000000001000111100 (
b00000000000000000000001001000000 )
b00000000000000000000001001000000 *
#311
0$
#312
1$
b00000000000000000000001001000000 '
b00000000000000000000001001000000 (
b00000000000000000000001001000100 )
b00000000000000000000001001000100 *
#313
0$
#314
1$
b00000000000000000000001001000100 '
b00000000000000000000001001000100 (
b00000000000000000000001001001000 )
b00000000000000000000001001001000 *
#315
0$
#316
1$
b00000000000000000000001001001000 '
b00000000000000000000001001001000 (
b00000000000000000000001001001100 )
b00000000000000000000001001001100 *
#317
0$
#318
1$
b00000000000000000000001001001100 '
b00000000000000000000001001001100 (
b00000000000000000000001001010000 )
b00000000000000000000001001010000 *
#319
0$
#320
1$
b00000000000000000000001001010000 '
b00000000000000000000001001010000 (
b00000000000000000000001001010100 )
b00000000000000000000001001010100 *
#321
0$
#322
1$
b00000000000000000000001001010100 '
b00000000000000000000001001010100 (
b00000000000000000000001001011000 )
b00000000000000000000001001011000 *
#323
0$
#324
1$
b00000000000000000000001001011000 '
b00000000000000000000001001011000 (
b00000000000000000000001001011100 )
b00000000000000000000001001011100 *
#325
0$
#326
1$
b00000000000000000000001001011100 '
b00000000000000000000001001011100 (
b00000000000000000000001001100000 )
b00000000000000000000001001100000 *
#327
0$
#328
1$
b00000000000000000000001001100000 '
b00000000000000000000001001100000 (
b00000000000000000000001001100100 )
b00000000000000000000001001100100 *
#329
0$
#330
1$
b00000000000000000000001001100100 '
b00000000000000000000001001100100 (
b00000000000000000000001001101000 )
b00000000000000000000001001101000 *
#331
0$
#332
1$
b00000000000000000000001001101000 '
b00000000000000000000001001101000 (
b00000000000000000000001001101100 )
b00000000000000000000001001101100 *
#333
0$
#334
1$
b00000000000000000000001001101100 '
b00000000000000000000001001101100 (
b00000000000000000000001001110000 )
b00000000000000000000001001110000 *
#335
0$
#336
1$
b00000000000000000000001001110000 '
b00000000000000000000001001110000 (
b00000000000000000000001001110100 )
b00000000000000000000001001110100 *
#337
0$
#338
1$
b00000000000000000000001001110100 '
b00000000000000000000001001110100 (
b00000000000000000000001001111000 )
b00000000000000000000001001111000 *
#339
0$
#340
1$
b00000000000000000000001001111000 '
b00000000000000000000001001111000 (
b00000000000000000000001001111100 )
b00000000000000000000001001111100 *
#341
0$
#342
1$
b00000000000000000000001001111100 '
b00000000000000000000001001111100 (
b00000000000000000000001010000000 )
b00000000000000000000001010000000 *
#343
0$
#344
1$
b00000000000000000000001010000000 '
b00000000000000000000001010000000 (
b00000000000000000000001010000100 )
b00000000000000000000001010000100 *
#345
0$
#346
1$
b00000000000000000000001010000100 '
b00000000000000000000001010000100 (
b00000000000000000000001010001000 )
b00000000000000000000001010001000 *
#347
0$
#348
1$
b00000000000000000000001010001000 '
b00000000000000000000001010001000 (
b00000000000000000000001010001100 )
b00000000000000000000001010001100 *
#349
0$
#350
1$
b00000000000000000000001010001100 '
b00000000000000000000001010001100 (
b00000000000000000000001010010000 )
b00000000000000000000001010010000 *
#351
0$
#352
1$
b00000000000000000000001010010000 '
b00000000000000000000001010010000 (
b00000000000000000000001010010100 )
b00000000000000000000001010010100 *
#353
0$
#354
1$
b00000000000000000000001010010100 '
b00000000000000000000001010010100 (
b00000000000000000000001010011000 )
b00000000000000000000001010011000 *
#355
0$
#356
1$
b00000000000000000000001010011000 '
b00000000000000000000001010011000 (
b00000000000000000000001010011100 )
b00000000000000000000001010011100 *
#357
0$
#358
1$
b00000000000000000000001010011100 '
b00000000000000000000001010011100 (
b00000000000000000000001010100000 )
b00000000000000000000001010100000 *
#359
0$
#360
1$
b00000000000000000000001010100000 '
b00000000000000000000001010100000 (
b00000000000000000000001010100100 )
b00000000000000000000001010100100 *
#361
0$
#362
1$
b00000000000000000000001010100100 '
b00000000000000000000001010100100 (
b00000000000000000000001010101000 )
b00000000000000000000001010101000 *
#363
0$
#364
1$
b00000000000000000000001010101000 '
b00000000000000000000001010101000 (
b00000000000000000000001010101100 )
b00000000000000000000001010101100 *
#365
0$
#366
1$
b00000000000000000000001010101100 '
b00000000000000000000001010101100 (
b00000000000000000000001010110000 )
b00000000000000000000001010110000 *
#367
0$
#368
1$
b00000000000000000000001010110000 '
b00000000000000000000001010110000 (
b00000000000000000000001010110100 )
b00000000000000000000001010110100 *
#369
0$
#370
1$
b00000000000000000000001010110100 '
b00000000000000000000001010110100 (
b00000000000000000000001010111000 )
b00000000000000000000001010111000 *
#371
0$
#372
1$
b00000000000000000000001010111000 '
b00000000000000000000001010111000 (
b00000000000000000000001010111100 )
b00000000000000000000001010111100 *
#373
0$
#374
1$
b00000000000000000000001010111100 '
b00000000000000000000001010111100 (
b00000000000000000000001011000000 )
b00000000000000000000001011000000 *
#375
0$
#376
1$
b00000000000000000000001011000000 '
b00000000000000000000001011000000 (
b00000000000000000000001011000100 )
b00000000000000000000001011000100 *
#377
0$
#378
1$
b00000000000000000000001011000100 '
b00000000000000000000001011000100 (
b00000000000000000000001011001000 )
b00000000000000000000001011001000 *
#379
0$
#380
1$
b00000000000000000000001011001000 '
b00000000000000000000001011001000 (
b00000000000000000000001011001100 )
b00000000000000000000001011001100 *
#381
0$
#382
1$
b00000000000000000000001011001100 '
b00000000000000000000001011001100 (
b00000000000000000000001011010000 )
b00000000000000000000001011010000 *
#383
0$
#384
1$
b00000000000000000000001011010000 '
b00000000000000000000001011010000 (
b00000000000000000000001011010100 )
b00000000000000000000001011010100 *
#385
0$
#386
1$
b00000000000000000000001011010100 '
b00000000000000000000001011010100 (
b00000000000000000000001011011000 )
b00000000000000000000001011011000 *
#387
0$
#388
1$
b00000000000000000000001011011000 '
b00000000000000000000001011011000 (
b00000000000000000000001011011100 )
b00000000000000000000001011011100 *
#389
0$
#390
1$
b00000000000000000000001011011100 '
b00000000000000000000001011011100 (
b00000000000000000000001011100000 )
b00000000000000000000001011100000 *
#391
0$
#392
1$
b00000000000000000000001011100000 '
b00000000000000000000001011100000 (
b00000000000000000000001011100100 )
b00000000000000000000001011100100 *
#393
0$
#394
1$
b00000000000000000000001011100100 '
b00000000000000000000001011100100 (
b00000000000000000000001011101000 )
b00000000000000000000001011101000 *
#395
0$
#396
1$
b00000000000000000000001011101000 '
b00000000000000000000001011101000 (
b00000000000000000000001011101100 )
b00000000000000000000001011101100 *
#397
0$
#398
1$
b00000000000000000000001011101100 '
b00000000000000000000001011101100 (
b00000000000000000000001011110000 )
b00000000000000000000001011110000 *
#399
0$
