Task4/InstructionMemory/instr_mem.sv
module instr_mem (
    input logic [31:0]               A,
    output logic [31:0]              RD
);

logic [31:0] rom_array[0:31];

initial begin
    $readmemh("instruction.mem", rom_array);
end;

assign RD = rom_array [A];

endmodule

Task4/InstructionMemory/instr_mem.vcd
$version Generated by VerilatedVcd $end
$date Thu Dec  8 10:44:06 2022 $end
$timescale 1ps $end

 $scope module TOP $end
  $var wire 32 C A [31:0] $end
  $var wire 32 D RD [31:0] $end
  $scope module instr_mem $end
   $var wire 32 C A [31:0] $end
   $var wire 32 D RD [31:0] $end
   $var wire 32 # rom_array[0] [31:0] $end
   $var wire 32 - rom_array[10] [31:0] $end
   $var wire 32 . rom_array[11] [31:0] $end
   $var wire 32 / rom_array[12] [31:0] $end
   $var wire 32 0 rom_array[13] [31:0] $end
   $var wire 32 1 rom_array[14] [31:0] $end
   $var wire 32 2 rom_array[15] [31:0] $end
   $var wire 32 3 rom_array[16] [31:0] $end
   $var wire 32 4 rom_array[17] [31:0] $end
   $var wire 32 5 rom_array[18] [31:0] $end
   $var wire 32 6 rom_array[19] [31:0] $end
   $var wire 32 $ rom_array[1] [31:0] $end
   $var wire 32 7 rom_array[20] [31:0] $end
   $var wire 32 8 rom_array[21] [31:0] $end
   $var wire 32 9 rom_array[22] [31:0] $end
   $var wire 32 : rom_array[23] [31:0] $end
   $var wire 32 ; rom_array[24] [31:0] $end
   $var wire 32 < rom_array[25] [31:0] $end
   $var wire 32 = rom_array[26] [31:0] $end
   $var wire 32 > rom_array[27] [31:0] $end
   $var wire 32 ? rom_array[28] [31:0] $end
   $var wire 32 @ rom_array[29] [31:0] $end
   $var wire 32 % rom_array[2] [31:0] $end
   $var wire 32 A rom_array[30] [31:0] $end
   $var wire 32 B rom_array[31] [31:0] $end
   $var wire 32 & rom_array[3] [31:0] $end
   $var wire 32 ' rom_array[4] [31:0] $end
   $var wire 32 ( rom_array[5] [31:0] $end
   $var wire 32 ) rom_array[6] [31:0] $end
   $var wire 32 * rom_array[7] [31:0] $end
   $var wire 32 + rom_array[8] [31:0] $end
   $var wire 32 , rom_array[9] [31:0] $end
  $upscope $end
 $upscope $end
$enddefinitions $end


#0
b00000000000000000000000000000000 #
b00000000000000000000000000000000 $
b00000000000000000000000000000000 %
b00000000000000000000000000000000 &
b00000000000000000000000000000000 '
b00000000000000000000000000000000 (
b00000000000000000000000000000000 )
b00000000000000000000000000000000 *
b00000000000000000000000000000000 +
b00000000000000000000000000000000 ,
b00000000000000000000000000000000 -
b00000000000000000000000000000000 .
b00000000000000000000000000000000 /
b00000000000000000000000000000000 0
b00000000000000000000000000000000 1
b00000000000000000000000000000000 2
b00000000000000000000000000000000 3
b00000000000000000000000000000000 4
b00000000000000000000000000000000 5
b00000000000000000000000000000000 6
b00000000000000000000000000000000 7
b00000000000000000000000000000000 8
b00000000000000000000000000000000 9
b00000000000000000000000000000000 :
b00000000000000000000000000000000 ;
b00000000000000000000000000000000 <
b00000000000000000000000000000000 =
b00000000000000000000000000000000 >
b00000000000000000000000000000000 ?
b00000000000000000000000000000000 @
b00000000000000000000000000000000 A
b00000000000000000000000000000000 B
b00000000000000000000000000000000 C
b00000000000000000000000000000000 D
#2
b00001111111100000000001100010011 #
b00000000000000000000010100010011 '
b00000000000000000000010110010011 +
b00000000000001011000010100010011 /
b00000000000101011000010110010011 3
b11111110011001011001110011100011 7
b11111110000000110001100011100011 ;
b00000000000000000000000000000001 C
b00001111111100000000001100010011 D
#4
b00000000000000000000000000000010 C
b00000000000000000000000000000000 D
#6
b00000000000000000000000000000011 C
#8
b00000000000000000000000000000100 C
#10
b00000000000000000000000000000101 C
b00000000000000000000010100010011 D
#12
b00000000000000000000000000000110 C
b00000000000000000000000000000000 D
#14
b00000000000000000000000000000111 C
#16
b00000000000000000000000000001000 C
#18
b00000000000000000000000000001001 C
b00000000000000000000010110010011 D
#20
b00000000000000000000000000001010 C
b00000000000000000000000000000000 D
#22
b00000000000000000000000000001011 C
#24
b00000000000000000000000000001100 C
#26
b00000000000000000000000000001101 C
b00000000000001011000010100010011 D
#28
b00000000000000000000000000001110 C
b00000000000000000000000000000000 D
#30
b00000000000000000000000000001111 C
#32
b00000000000000000000000000010000 C
#34
b00000000000000000000000000010001 C
b00000000000101011000010110010011 D
#36
b00000000000000000000000000010010 C
b00000000000000000000000000000000 D
#38
b00000000000000000000000000010011 C
#40
b00000000000000000000000000010100 C
#42
b00000000000000000000000000010101 C
b11111110011001011001110011100011 D
#44
b00000000000000000000000000010110 C
b00000000000000000000000000000000 D
#46
b00000000000000000000000000010111 C
#48
b00000000000000000000000000011000 C
#50
b00000000000000000000000000011001 C
b11111110000000110001100011100011 D
#52
b00000000000000000000000000011010 C
b00000000000000000000000000000000 D
#54
b00000000000000000000000000011011 C
#56
b00000000000000000000000000011100 C
#58
b00000000000000000000000000011101 C
#60
b00000000000000000000000000011110 C
#62
b00000000000000000000000000011111 C
#64
b00000000000000000000000000100000 C
#66
b00000000000000000000000000100001 C
b00001111111100000000001100010011 D
#68
b00000000000000000000000000100010 C
b00000000000000000000000000000000 D
#70
b00000000000000000000000000100011 C
#72
b00000000000000000000000000100100 C
#74
b00000000000000000000000000100101 C
b00000000000000000000010100010011 D
#76
b00000000000000000000000000100110 C
b00000000000000000000000000000000 D
#78
b00000000000000000000000000100111 C
#80
b00000000000000000000000000101000 C
#82
b00000000000000000000000000101001 C
b00000000000000000000010110010011 D
#84
b00000000000000000000000000101010 C
b00000000000000000000000000000000 D
#86
b00000000000000000000000000101011 C
#88
b00000000000000000000000000101100 C
#90
b00000000000000000000000000101101 C
b00000000000001011000010100010011 D
#92
b00000000000000000000000000101110 C
b00000000000000000000000000000000 D
#94
b00000000000000000000000000101111 C
#96
b00000000000000000000000000110000 C
#98
b00000000000000000000000000110001 C
b00000000000101011000010110010011 D
#100
b00000000000000000000000000110010 C
b00000000000000000000000000000000 D
#102
b00000000000000000000000000110011 C
#104
b00000000000000000000000000110100 C
#106
b00000000000000000000000000110101 C
b11111110011001011001110011100011 D
#108
b00000000000000000000000000110110 C
b00000000000000000000000000000000 D
#110
b00000000000000000000000000110111 C
#112
b00000000000000000000000000111000 C
#114
b00000000000000000000000000111001 C
b11111110000000110001100011100011 D
#116
b00000000000000000000000000111010 C
b00000000000000000000000000000000 D
#118
b00000000000000000000000000111011 C
#120
b00000000000000000000000000111100 C
#122
b00000000000000000000000000111101 C
#124
b00000000000000000000000000111110 C
#126
b00000000000000000000000000111111 C
