legacy/Task4/InstructionMemory/instr_mem.sv
module instr_mem (
    input logic [31:0]               A,
    output logic [31:0]              RD
);

logic [7:0] rom_array[0:27];

initial begin
    $readmemh("instruction.mem", rom_array);
end;

assign RD = {rom_array[A], rom_array[A+1], rom_array[A+2], rom_array[A+3]};

endmodule

legacy/Task4/InstructionMemory/instr_mem.vcd
$version Generated by VerilatedVcd $end
$date Thu Dec  8 11:12:45 2022 $end
$timescale 1ps $end

 $scope module TOP $end
  $var wire 32 ? A [31:0] $end
  $var wire 32 @ RD [31:0] $end
  $scope module instr_mem $end
   $var wire 32 ? A [31:0] $end
   $var wire 32 @ RD [31:0] $end
   $var wire  8 # rom_array[0] [7:0] $end
   $var wire  8 - rom_array[10] [7:0] $end
   $var wire  8 . rom_array[11] [7:0] $end
   $var wire  8 / rom_array[12] [7:0] $end
   $var wire  8 0 rom_array[13] [7:0] $end
   $var wire  8 1 rom_array[14] [7:0] $end
   $var wire  8 2 rom_array[15] [7:0] $end
   $var wire  8 3 rom_array[16] [7:0] $end
   $var wire  8 4 rom_array[17] [7:0] $end
   $var wire  8 5 rom_array[18] [7:0] $end
   $var wire  8 6 rom_array[19] [7:0] $end
   $var wire  8 $ rom_array[1] [7:0] $end
   $var wire  8 7 rom_array[20] [7:0] $end
   $var wire  8 8 rom_array[21] [7:0] $end
   $var wire  8 9 rom_array[22] [7:0] $end
   $var wire  8 : rom_array[23] [7:0] $end
   $var wire  8 ; rom_array[24] [7:0] $end
   $var wire  8 < rom_array[25] [7:0] $end
   $var wire  8 = rom_array[26] [7:0] $end
   $var wire  8 > rom_array[27] [7:0] $end
   $var wire  8 % rom_array[2] [7:0] $end
   $var wire  8 & rom_array[3] [7:0] $end
   $var wire  8 ' rom_array[4] [7:0] $end
   $var wire  8 ( rom_array[5] [7:0] $end
   $var wire  8 ) rom_array[6] [7:0] $end
   $var wire  8 * rom_array[7] [7:0] $end
   $var wire  8 + rom_array[8] [7:0] $end
   $var wire  8 , rom_array[9] [7:0] $end
  $upscope $end
 $upscope $end
$enddefinitions $end


#0
b00000000 #
b00000000 $
b00000000 %
b00000000 &
b00000000 '
b00000000 (
b00000000 )
b00000000 *
b00000000 +
b00000000 ,
b00000000 -
b00000000 .
b00000000 /
b00000000 0
b00000000 1
b00000000 2
b00000000 3
b00000000 4
b00000000 5
b00000000 6
b00000000 7
b00000000 8
b00000000 9
b00000000 :
b00000000 ;
b00000000 <
b00000000 =
b00000000 >
b00000000000000000000000000000000 ?
b00000000000000000000000000000000 @
#2
b00001111 #
b11110000 $
b00000011 %
b00010011 &
b00000101 )
b10010011 *
b00000101 ,
b10000101 -
b00010011 .
b00010101 0
b10000101 1
b10010011 2
b11111110 3
b01100101 4
b10011100 5
b11100011 6
b11111110 7
b00000011 8
b00011000 9
b00000000000000000000000000000100 ?
b00001111111100000000001100010011 @
#4
b00000000000000000000000000001000 ?
b00000000000000000000010110010011 @
#6
b00000000000000000000000000001100 ?
b00000000000001011000010100010011 @
#8
b00000000000000000000000000010000 ?
b00000000000101011000010110010011 @
#10
b00000000000000000000000000010100 ?
b11111110011001011001110011100011 @
#12
b00000000000000000000000000011000 ?
b11111110000000110001100000000000 @
#14
b00000000000000000000000000011100 ?
b00000000000000000000000000000000 @
#16
b00000000000000000000000000100000 ?
#18
b00000000000000000000000000100100 ?
b00001111111100000000001100010011 @
#20
b00000000000000000000000000101000 ?
b00000000000000000000010110010011 @
#22
b00000000000000000000000000101100 ?
b00000000000001011000010100010011 @
#24
b00000000000000000000000000110000 ?
b00000000000101011000010110010011 @
#26
b00000000000000000000000000110100 ?
b11111110011001011001110011100011 @
#28
b00000000000000000000000000111000 ?
b11111110000000110001100000000000 @
#30
b00000000000000000000000000111100 ?
b00000000000000000000000000000000 @
#32
b00000000000000000000000001000000 ?
#34
b00000000000000000000000001000100 ?
b00001111111100000000001100010011 @
#36
b00000000000000000000000001001000 ?
b00000000000000000000010110010011 @
#38
b00000000000000000000000001001100 ?
b00000000000001011000010100010011 @
#40
b00000000000000000000000001010000 ?
b00000000000101011000010110010011 @
#42
b00000000000000000000000001010100 ?
b11111110011001011001110011100011 @
#44
b00000000000000000000000001011000 ?
b11111110000000110001100000000000 @
#46
b00000000000000000000000001011100 ?
b00000000000000000000000000000000 @
#48
b00000000000000000000000001100000 ?
#50
b00000000000000000000000001100100 ?
b00001111111100000000001100010011 @
#52
b00000000000000000000000001101000 ?
b00000000000000000000010110010011 @
#54
b00000000000000000000000001101100 ?
b00000000000001011000010100010011 @
